Workbook

Sheet Жами топшириқлар-1
A1: Вилоят ҳокими У.Қосимов томонидан ҳудудларни ўрганиш давомида аниқланган муаммоларни бартараф этиш бўйича берилаётган тезкор топшириқларнинг ижроси тўғрисида МАЪЛУМОТ (10.11.2025)
A2: Банд | B2: Топшириқ берилган сана | C2: Топшириқ берилган жой | D2: Топшириқ мазмуни | E2: Ижро муддати | F2: Назорат ҳолати | G2: Асосий ижрочи маъсуллар | H2: Вилоят ҳокимлиги, шаҳар ва туман ҳокимликларидан масъуллар | I2: Ижро ҳолати | J2: Изох | M2: Ойлар кесимида | N2: Мажмуалар ва туманлар | P2: =SUM(P3:P1048576) -> 0 | Q2: 45066 | R2: Чоршанба кунгача | T2: Кўриб чиқиш | V2: мчс
A3: 1 | B3: 44922 | C3: Мажмуа ва ташкилотлар | D3: Куз-қиш бўйича тузилган штабларга келиб тушган, назоратга олинган ва ечилган мурожаатларни бўйича ҳарбийларни бириктириш. | E3: 44936 | G3: Вилоят ҳокимлиги гуруҳ раҳбари А.Каримов | H3: З.Назаров | I3: Бажарилган | M3: Январ | N3: Мажмуалар | O3: 1 | P3: =+O3-A3 -> 0 | T3: =+I3 -> Бажарилган
A4: 2 | B4: 44922 | C4: Мажмуа ва ташкилотлар | D4: Ишлаб чиқариш йирик лойиҳаларни шакллантириб, лойиҳа ташабускорлар билан учрашув ўтказиш. | E4: 44931 | G4: Марказий банк вилоят бош бошқармаси (А.Тўхтаев) | H4: Ш.Жўраев | I4: Бажарилган | M4: Январ | N4: Мажмуалар | O4: =+O3+1 -> 2 | P4: =+O4-A4 -> 0 | T4: =+J4 -> 0
A5: 3 | B5: 44922 | C5: Мажмуа ва ташкилотлар | D5: Ҳудудларга тўғридан-тўғри инвестицияларни жалб қилиш, экспорт прогноз режасини ҳафталик ва ойлик графикларини туман (шаҳар) ва секторлар кесимида ишлаб чиқсин, прогнозларнинг бажарилишини назорат қилиш. | E5: 45092 | F5: Доимий | G5: Вилоят ҳокимининг ўринбосари А.Орипов | H5: Ш.Жўраев | I5: Бажарилган | M5: Январ | N5: Мажмуалар | O5: =+O4+1 -> 3 | P5: =+O5-A5 -> 0 | T5: =+J5 -> 0
A6: 4 | B6: 44923 | C6: Термиз шаҳар | D6: Термиз иқтисодий зона ва кичик саноат зоналари фаолиятини яхшилаш, бўш турган ер майдонларини тадбиркорлик фаолиятини йўлга қўйиш, ҳамда ишлаб чиқариш лойиҳаларини амалга ошириш. | E6: 45092 | F6: Доимий | G6: “Термиз” эркин иқтисодий зонаси Дирекцияси ДУК (Б.Жумаев),“Кичик саноат зоналарини бошқариш ягона дирекцияси” (Б.Ортиқов) | H6: Ш.Жўраев | I6: Бажарилган | M6: Январ | N6: Мажмуалар | O6: =+O5+1 -> 4 | P6: =+O6-A6 -> 0 | T6: =+J6 -> 0
A7: 5 | B7: 44923 | C7: Термиз шаҳар | D7: Термиз шаҳар ва туманларда янги кичик саноат зоналарини ташкил этиш таклифларини ишлаб чиқиш. | E7: 44931 | G7: “Кичик саноат зоналарини бошқариш ягона дирекцияси” (Б.Ортиқов) Термиз шаҳар ва туманлар ҳокимликлари | H7: Ш.Жўраев | I7: Бажарилган | M7: Январ | N7: Мажмуалар | O7: =+O6+1 -> 5 | P7: =+O7-A7 -> 0 | T7: =+J7 -> 0
A8: 6 | B8: 44923 | C8: Термиз шаҳар | D8: “Термиз халқаро савдо маркази” ЭСЗни ишга тушириш, муаммоли масалаларнинг тезкор ечимига қаратилган таклифлар ишлаб чиқиб, вилоят ҳокимига ахборот бериш. | E8: 44929 | G8: Вилоят ҳокимининг ўринбосари А.Орипов | H8: Ш.Жўраев | I8: Бажарилган | M8: Январ | N8: Мажмуалар | O8: =+O7+1 -> 6 | P8: =+O8-A8 -> 0 | T8: =+J8 -> 0
A9: 7 | B9: 44923 | C9: Термиз шаҳар | D9: “Термиз халқаро савдо маркази” ЭСЗнинг қурилиши учун олинган кредит маблағларини қайтариш муддатини узайтириш бўйича алоқадор вазирлик ва идоралар билан ҳамкорликда ишларни ташкил этиш. | E9: 44957 | G9: Вилоят ҳокимининг ўринбосари А.Орипов | H9: Ш.Жўраев | I9: Бажарилган | M9: Январ | N9: Мажмуалар | O9: =+O8+1 -> 7 | P9: =+O9-A9 -> 0 | T9: =+J9 -> 0
A10: 8 | B10: 44923 | C10: Термиз шаҳар | D10: Вилоят тадбиркорлари томонидан Покистондан импорт қилиб олиб келинаётган картошка маҳсулотларини олиб киришда юзага келаётган муаммоларни таҳлил қилиш ва ҳал этиш чораларини кўриш. | E10: 44931 | G10: Вилоят ҳокимининг ўринбосари А.Орипов | H10: Ш.Жўраев | I10: Бажарилган | M10: Январ | N10: Мажмуалар | O10: =+O9+1 -> 8 | P10: =+O10-A10 -> 0 | T10: =+J10 -> 0
A11: 9 | B11: 44923 | C11: Термиз шаҳар | D11: “Термиз” ЭИЗдаги бўш турган ер майдонлари (лотлар)ни аукцион савдоларига чиқариш ишларини жадаллаштириш. | E11: 44959 | G11: Вилоят ҳокимининг ўринбосари А.Орипов, “Термиз” ЭИЗ дирекцияси ДУК (Жумаев) | H11: Ш.Жўраев | I11: Бажарилган | M11: Январ | N11: Мажмуалар | O11: =+O10+1 -> 9 | P11: =+O11-A11 -> 0 | T11: =+J11 -> 0
A12: 10 | B12: 44923 | C12: Термиз шаҳар | D12: “Термиз” ЭИЗдаги ер майдонларини (лотлар)ни тижорат банклари кесимида бириктириш ва истиқболли лойиҳа таклифларини ишлаб чиқиш. | E12: 44941 | G12: Вилоят ҳокимининг ўринбосари А.Орипов, “Термиз” ЭИЗ дирекцияси ДУК (Жумаев), Марказий банк бош бошқармаси (Тўхтаев) ва тижорат банклари | H12: Ш.Жўраев | I12: Бажарилган | M12: Январ | N12: Мажмуалар | O12: =+O11+1 -> 10 | P12: =+O12-A12 -> 0 | T12: =+J12 -> 0
A13: 11 | B13: 44925 | C13: Денов тумани | D13: “Денов текстил кластер” МЧЖ (97-844-00-00) томонидан амалга оширилаётган инвестиция лойиҳасини муддатида ишга туширилиши учун кредит маблағлари ажратилишини ҳал этиш. | E13: 45285 | F13: Охирги муддат бошқа узайтирилмайди | G13: Ташқи иқтисодий фаолият Миллий банки АЖ филиали (Ш.Жумаев). | H13: Ш.Жўраев | I13: Бажарилган | J13: 08.08.2023 й кун ҳолатига келиб хам тадбиркор кредит қарздорлигини тўламаган. "Денов текстил кластер" МЧЖ ва Ўзмиллийбанк АЖ ўртасида "Саноат ипотекаси" ҳисобидан 25 млн АҚШ долл миқдорида молиялаштириш лойихаси ишлари амалга оширилмоқда. Лойихани 1-босқичини 2023 йил 4-чорагида молиялаштириш режалаштириляпти. Охирги муддат берилди бошқа узайтирилмайди | M13: Январ | N13: Мажмуалар | O13: =+O12+1 -> 11 | P13: =+O13-A13 -> 0 | T13: =+J13 -> 08.08.2023 й кун ҳолатига келиб хам тадбиркор кредит қарздорлигини тўламаган. "Денов текстил кластер" МЧЖ ва Ўзмиллийбанк АЖ ўртасида "Саноат ипотекаси" ҳисобидан 25 млн АҚШ долл миқдорида молиялаштириш лойихаси ишлари амалга оширилмоқда. Лойихани 1-босқичини 2023 йил 4-чорагида молиялаштириш режалаштириляпти. Охирги муддат берилди бошқа узайтирилмайди
A14: 12 | B14: 44925 | C14: Денов тумани | D14: “Денов текстил кластер” МЧЖ томонидан 2 гектар майдонда гул етиштириш учун иссиқхона ташкил этиш бўйича лойиҳа тақдимотини ўтказиш. | E14: 44944 | G14: Вилоят ҳокимнинг ўринбосари А.Орипов Денов тумани ҳокимлиги (Алламуродов), “Денов текстил кластер” МЧЖ | H14: Ш.Жўраев | I14: Бажарилган | M14: Январ | N14: Мажмуалар | O14: =+O13+1 -> 12 | P14: =+O14-A14 -> 0 | T14: =+J14 -> 0
A15: 13 | B15: 44925 | C15: Денов тумани | D15: Денов туманидаги “Мармар” МЧЖ томонидан амалга оширилаётган лойиҳани муддатида ишга тушишини таъминлаш мақсадида кредит маблағлари ажратилишини таъминлаш. | E15: 45112 | F15: Билдирги | G15: ТИФ Миллий банк (Жумаев) | H15: Ш.Жўраев | I15: Бажарилган | M15: Январ | N15: Мажмуалар | O15: =+O14+1 -> 13 | P15: =+O15-A15 -> 0 | T15: =+J15 -> 0
A16: 14 | B16: 44922 | C16: Шеробод тумани Зарабоғ қишлоғи | D16: Шеробод туманидаги "Туз кони" имкониятларидан самарали фойдаланиш мақсадида даволаш бўйича туристларни жалб қилиш лойиҳасини ишлаб чиқиш. | E16: 44936 | G16: Вилоят ҳокимининг ўринбосарлари А.Орипов, Ж.Тўраев | H16: Ш.Жўраев | I16: Бажарилган | M16: Январ | N16: Мажмуалар | O16: =+O15+1 -> 14 | P16: =+O16-A16 -> 0 | T16: =+J16 -> 0
A17: 15 | B17: 44922 | C17: Термиз шаҳар | D17: Термиз шаҳар кичик саноат зонасидаги ички йўлларни таъмирлаш. | E17: 44985 | G17: "Сурхондарёавтойўл" корхонаси (У.Темиров) | H17: Ш.Жўраев | I17: Бажарилган | M17: Январ | N17: Мажмуалар | O17: =+O16+1 -> 15 | P17: =+O17-A17 -> 0 | T17: =+J17 -> 0
A18: 16 | B18: 44922 | C18: Термиз шаҳар | D18: Термиз шаҳридаги "Ал-Хоразмий ахборот технологиялари "ИТ" мактаби" нодавлат таълим муассасаси ташкил этиш учун кредит ажратилиши масаласини ҳал этиш. | E18: 45017 | F18: Билдирги | G18: Вилоят ҳокимининг ўринбосарлари А.Орипов Марказий банк бош бошқармаси (А.Тўхтаев) | H18: Ш.Жўраев | I18: Бажарилган | M18: Январ | N18: Мажмуалар | O18: =+O17+1 -> 16 | P18: =+O18-A18 -> 0 | T18: =+J18 -> 0
A19: 17 | B19: 44922 | C19: Термиз шаҳри | D19: Реновацияга тушган биноларни таъмирлаш масаласида қурилиш пудрат корхоналари раҳбарлари билан учрашиш ва инвесторларни аниқлаш. | E19: 45127 | F19: Билдирги | G19: Термиз шаҳар ҳокими Ў.Тўраев | H19: А.Амиров | I19: Бажарилган | J19: Термиз Тезкор Қурилиш МЧЖга "Тупроққўрғон" мфй Дилнаво кўчасидан 1,16 га ер майдони ажратилган | M19: Январ | N19: Мажмуалар | O19: =+O18+1 -> 17 | P19: =+O19-A19 -> 0 | Q19: 45066 | T19: =+J19 -> Термиз Тезкор Қурилиш МЧЖга "Тупроққўрғон" мфй Дилнаво кўчасидан 1,16 га ер майдони ажратилган
A20: 18 | B20: 44922 | C20: Термиз шаҳри | D20: Термиз шаҳри “Гулистон” маҳалласи Янги Ўзбекистон кўчасида асфальт ётқизиш, кўча ёритиш чироқлари ўрнатиш, йўл бўйлаб дарахт кўчатлари экиш, яшил ҳудудларни ташкил этиш ҳамда сувлаш тизимларини ўрнатиш ишларини якунлаш | E20: 44931 | G20: Вилоят Автомобиль йўлларидан фойдаланиш унитар корхонаси | H20: А.Амиров | I20: Бажарилган | M20: Январ | N20: Мажмуалар | O20: =+O19+1 -> 18 | P20: =+O20-A20 -> 0 | T20: =+J20 -> 0
A21: 19 | B21: 44922 | C21: Термиз шаҳри | D21: Термиз шаҳри “Гулистон” маҳалласи Янги Ўзбекистон кўчасида олиб борилаётган қурилиш ишларини назорат қилиш | E21: 45174 | F21: Доимий | G21: Сурхондарё вилоят Ҳудудий назорат инспекцияси (ГАСН) Б.Назаров | H21: А.Амиров | I21: Бажарилган | M21: Январ | N21: Мажмуалар | O21: =+O20+1 -> 19 | P21: =+O21-A21 -> 0 | T21: =+J21 -> 0
A22: 20 | B22: 44922 | C22: Термиз шаҳри | D22: Термиз шаҳри Ибн Сино кўчасидаги сифатсиз қурилган саломатлик йўлагини қурилиши бўйича текширув ўтказиш, йўлакни бузиш ва қайтадан сифатли қуриш | E22: 45078 | F22: Билдирги | G22: Термиз шаҳар ҳокими Ў.Тўраев | H22: А.Амиров | I22: Бажарилган | M22: Январ | N22: Мажмуалар | O22: =+O21+1 -> 20 | P22: =+O22-A22 -> 0 | Q22: 45066 | T22: =+J22 -> 0
A23: 21 | B23: 44922 | C23: Термиз шаҳри | D23: Термиз шаҳридаги 16-сонли мактабда биносини таъмирлаш бўйича лойиҳа-смета ҳужжатларини ишлаб чиқиш | E23: 44936 | G23: Термиз шаҳар ҳокими Ў.Тўраев | H23: А.Амиров | I23: Бажарилган | M23: Январ | N23: Мажмуалар | O23: =+O22+1 -> 21 | P23: =+O23-A23 -> 0 | T23: =+J23 -> 0
A24: 22 | B24: 44922 | C24: Термиз шаҳри | D24: “Юбилейний” бозоридаги мавжуд ҳолатни ўрганиш бўйича ишчи гуруҳ тузиш, 2023 йил 20 январга қадар сотувчиларнинг ҳар бири билан гаплашиб, уларни кўчириш | E24: 44946 | G24: Вилоят ҳокимининг ўринбосари А.Хидиров, Термиз шаҳар ҳокими Ў.Тўраев | H24: А.Амиров | I24: Бажарилган | M24: Январ | N24: Мажмуалар | O24: =+O23+1 -> 22 | P24: =+O24-A24 -> 0 | T24: =+J24 -> 0
A25: 23 | B25: 44922 | C25: Термиз шаҳри | D25: “Юбилейний” бозори ҳудудида ўтувчи тунеллни таъмирлаш бўйича лойиҳа хужжатларини кайта куриб чикиш ва курилиш ишларини бошлаш. | E25: 44931 | G25: Вилоят ҳокимининг ўринбосари А.Хидиров, Вилоят Автомобиль йўлларидан фойдаланиш унитар корхонаси Термиз шаҳар ҳокими Ў.Тўраев | H25: А.Амиров | I25: Бажарилган | M25: Январ | N25: Мажмуалар | O25: =+O24+1 -> 23 | P25: =+O25-A25 -> 0 | T25: =+J25 -> 0
A26: 24 | B26: 44922 | C26: Термиз шаҳри | D26: Термиз шаҳри “Паттакесар” маҳалласи Нурли келажак кўчасидаги йўл таъмири лойиҳасини қайта кўриб чиқиш | E26: 44931 | G26: Вилоят ҳокимининг ўринбосари А.Хидиров, Термиз шаҳар ҳокими Ў.Тўраев | H26: А.Амиров | I26: Бажарилган | M26: Январ | N26: Мажмуалар | O26: =+O25+1 -> 24 | P26: =+O26-A26 -> 0 | T26: =+J26 -> 0
A27: 25 | B27: 44922 | C27: Термиз шаҳри | D27: Термиз шаҳри “Паттакесар” маҳалласи ҳудудидаги икки қаватли уйларни таъмирлаш бўйича штаб фаолиятини йўлга қўйиш | E27: 44931 | G27: Панжи Қобилов, Шахар ИИБ | H27: А.Амиров | I27: Бажарилган | M27: Январ | N27: Мажмуалар | O27: =+O26+1 -> 25 | P27: =+O27-A27 -> 0 | T27: =+J27 -> 0
A28: 26 | B28: 44922 | C28: Термиз шаҳри | D28: Термиз шаҳри “Паттакесар” маҳалласи ҳудудидаги икки қаватли уйларни том ва фасад қисмини таъмирлаш, болалар майдончаси, автотураргоҳ ташкил этиш, ободонлаштириш ишларини олиб бориш ва чиқиндиларни олиб чиқиш | E28: 44954 | F28: Билдирги | G28: Панжи Қобилов, Шахар ИИБ | H28: А.Амиров | I28: Бажарилган | M28: Январ | N28: Мажмуалар | O28: =+O27+1 -> 26 | P28: =+O28-A28 -> 0 | T28: =+J28 -> 0
A29: 27 | B29: 44922 | C29: Термиз шаҳри | D29: Термиз шаҳри “Паттакесар” маҳалласи ҳудудида қурилаётган арзон уйларни фойдаланишга топшириш | E29: 44986 | F29: Билдирги | G29: Вилоят Халқ қабулхонаси А.Эшмуродов Термиз шаҳар ҳокими Ў.Тўраев | H29: А.Амиров | I29: Бажарилган | M29: Январ | N29: Мажмуалар | O29: =+O28+1 -> 27 | P29: =+O29-A29 -> 0 | T29: =+J29 -> 0
A30: 28 | B30: 44922 | C30: Термиз шаҳри | D30: “Сурхон Саноат Қурилиш” компанияси томонидан Фаровон массивида қурилиши белгиланган кўп қаватли уй-жойлар лойиҳасида янги мактаб, мактабгача таълим ташкилоти ва бошқа ижтимоий объектларни лойиҳалаш ишлари ишлаб чиқиш | E30: 44923 | G30: Вилоят курилиш бош бошкармаси К.Эшматов Термиз шаҳар ҳокими Ў.Тўраев | H30: А.Амиров | I30: Бажарилган | M30: Январ | N30: Мажмуалар | O30: =+O29+1 -> 28 | P30: =+O30-A30 -> 0 | T30: =+J30 -> 0
A31: 29 | B31: 44922 | C31: Термиз шаҳри | D31: Термиз эркин иқтисодий зонасини электр энергияси билан таъминлаш лойиҳасини якунлаш бўйича тармоқ жадвалини ишлаб чиқиш. | E31: 44925 | G31: “Сурхондарё ҲЭТК” АЖ (М.Шамсиддинов) | H31: А.Амиров | I31: Бажарилган | M31: Январ | N31: Мажмуалар | O31: =+O30+1 -> 29 | P31: =+O31-A31 -> 0 | T31: =+J31 -> 0
A32: 30 | B32: 44922 | C32: Мажмуа ва ташкилотлар билан муаммоли масалалар юзасидан йиғилиш | D32: Хоразм вилояти тажрибасидан келиб чиқиб, вилоятдаги долзарб муаммоларни ҳал этиш чора-тадбирлар дастурини ишлаб чиқиш. | E32: 44925 | G32: “Сурхондарё сув таъминот” тизимдаги ходимларнинг иш ҳақи бўйича мавжуд қарздорликларни бир кун муддатда тўлиқ бартараф этиш. | H32: А.Амиров | I32: Бажарилган | M32: Январ | N32: Мажмуалар | O32: =+O31+1 -> 30 | P32: =+O32-A32 -> 0 | T32: =+J32 -> 0
A33: 31 | B33: 44922 | C33: Мажмуа ва ташкилотлар билан муаммоли масалалар юзасидан йиғилиш | D33: Вилоятдаги буюртмачи ва назорат қилувчи ташкилотларнинг техник назорат ходимларини жалб қилиб, 2022 йилда инвестиция дастури, “Обод қишлоқ”, “Обод маҳалла” ва бошқа мақсадли дастурлар доирасида амалга оширилган қурилиш таъмирлаш ишлари сифатини кўриб чиқиб, мавжуд камчиликларни бартараф этиш чоралари белгилаш. | E33: 44936 | G33: Вилоят ҳокимининг ўринбосари А.Хидиров, алоқадор ташкилот ва корхоналар, Термиз шаҳар ва туманлар ҳокимликлари | H33: А.Амиров | I33: Бажарилган | M33: Январ | N33: Мажмуалар | O33: =+O32+1 -> 31 | P33: =+O33-A33 -> 0 | T33: =+J33 -> 0
A34: 32 | B34: 44922 | C34: Мажмуа ва ташкилотлар билан муаммоли масалалар юзасидан йиғилиш | D34: Термиз шаҳар ва Термиз тумани марказий автомобиль йўллари атрофларига манзарали кўчатларни экиш бўйича таклифлар ишлаб чиқиш. | E34: 44936 | G34: Вилоят ҳокимининг ўринбосари А.Хидиров, “Сурхондарёавтойўл” (У.Темиров) Термиз шаҳар ва туманлар ҳокимлари | H34: А.Амиров | I34: Бажарилган | M34: Январ | N34: Мажмуалар | O34: =+O33+1 -> 32 | P34: =+O34-A34 -> 0 | T34: =+J34 -> 0
A35: 33 | B35: 44922 | C35: Мажмуа ва ташкилотлар билан муаммоли масалалар юзасидан йиғилиш | D35: Аҳоли учун қўлай ва зарур коммуникациялар мавжуд бўлган ҳудудларда кўп қаватли уй-жойларни қуриш таклифларни ишлаб чиқиш. | E35: 44936 | G35: Вилоят Қурилиш бошқармаси (К.Эшматов), Термиз шаҳар ва туманлар ҳокимлари | H35: А.Амиров | I35: Бажарилган | M35: Январ | N35: Мажмуалар | O35: =+O34+1 -> 33 | P35: =+O35-A35 -> 0 | T35: =+J35 -> 0
A36: 34 | B36: 44922 | C36: Мажмуа ва ташкилотлар билан муаммоли масалалар юзасидан йиғилиш | D36: “Яшил макон” дастури доирасида кўп йиллик дарахт кўчатларини экиш, суғориш тизимини ташкил этиш. Вилоятдаги мавжуд кўп йиллик дарахтларни инвентаризациядан ўтказиб, уларни сақлаш учун далолатномалар асосида жойлардаги маҳаллалар раислари ва тегишли ташкилотлар ва корхоналарга топшириш. | E36: 45170 | F36: Билдирги | G36: Термиз шаҳар ва туманлар ҳокимликлари, Вилоят Экология ва атроф-муҳитни муҳофаза қилиш бошқармаси (Р.Сафарова) | H36: А.Амиров | I36: Бажарилган | M36: Январ | N36: Мажмуалар | O36: =+O35+1 -> 34 | P36: =+O36-A36 -> 0 | T36: =+J36 -> 0
A37: 35 | B37: 44922 | C37: Мажмуа ва ташкилотлар билан муаммоли масалалар юзасидан йиғилиш | D37: Вилоятдаги инвестиция дастури доирасида ижтимоий соҳа объектларини таъмирлаш ва реконструкция қилиш ишларини сифатини ўрнатилган тартибда кўриб чиқсин. | E37: 45044 | G37: Вилоят прокуратураси (келишув асосида) | H37: А.Амиров | I37: Бажарилган | M37: Январ | N37: Мажмуалар | O37: =+O36+1 -> 35 | P37: =+O37-A37 -> 0 | T37: =+J37 -> 0
A38: 36 | B38: 44922 | C38: Мажмуа ва ташкилотлар билан муаммоли масалалар юзасидан йиғилиш | D38: Вилоятдаги автомобиль йўлларини аҳволи ва уларни таъмирлаш ва реконструкция қилиш бўйича таклифларни ишлаб чиқиш. Бунда, автомобиль йўллар атрофларига кўп дарахтларни экишни назарда тутиш. | E38: 44931 | G38: “Сурхондарёавтойўл” ҳудудий йўллардан фойдаланиш ташкилоти (У.Темиров): | H38: А.Амиров | I38: Бажарилган | M38: Январ | N38: Мажмуалар | O38: =+O37+1 -> 36 | P38: =+O38-A38 -> 0 | T38: =+J38 -> 0
A39: 37 | B39: 44922 | C39: Мажмуа ва ташкилотлар билан муаммоли масалалар юзасидан йиғилиш | D39: Термиз ҳалқаро аэропортидан Термиз шаҳри ҳудудига қадар автомобиль йўллари атрофлари ободонлаштириш ва кўп йиллик дарахтларни экиш. | E39: 44984 | F39: Билдирги | G39: Термиз туман ҳокими Ш.Назаров, “Йўл кўкалам” ДУК (Б.Абраев) | H39: Термиз тумани | I39: Бажарилган | M39: Январ | N39: туманлар | O39: =+O38+1 -> 37 | P39: =+O39-A39 -> 0 | T39: =+J39 -> 0
A40: 38 | B40: 44922 | C40: Мажмуа ва ташкилотлар билан муаммоли масалалар юзасидан йиғилиш | D40: “Сурхондарё сув таъминот” тизимдаги ходимларнинг иш ҳақи бўйича мавжуд қарздорликларни бир кун муддатда тўлиқ бартараф этиш. | E40: 44931 | G40: “Сурхондарё сув таъминот” МЧЖ (Х.Сафоев) | H40: А.Амиров | I40: Бажарилган | M40: Январ | N40: Мажмуалар | O40: =+O39+1 -> 38 | P40: =+O40-A40 -> 0 | T40: =+J40 -> 0
A41: 39 | B41: 44922 | C41: Мажмуа ва ташкилотлар билан муаммоли масалалар юзасидан йиғилиш | D41: 2023 йилнинг 1 февралига қадар мавжуд дебитор қарздорликларни камида 50 фоизга қисқартириш. | E41: 45080 | F41: Доимий | G41: “Сурхондарё сув таъминот” МЧЖ (Х.Сафоев) | H41: А.Амиров | I41: Бажарилган | J41: Ҳозирги кунда 758 та 745 млн сўмлик судга ҳужжат тақдим қилинди. | M41: Январ | N41: Мажмуалар | O41: =+O40+1 -> 39 | P41: =+O41-A41 -> 0 | T41: =+J41 -> Ҳозирги кунда 758 та 745 млн сўмлик судга ҳужжат тақдим қилинди.
A42: 40 | B42: 44922 | C42: Мажмуа ва ташкилотлар билан муаммоли масалалар юзасидан йиғилиш | D42: Вилоятда мавжуд чиқиндиларни ҳудудлардан олиб чиқиш тизими яхшилаш ва хизмат кўрсатиш қамровини ошириш бўйича таклифларни ишлаб чиқсин. | E42: 44936 | G42: “Тоза ҳудуд” ДУК (Бегимқулов) | H42: А.Амиров | I42: Бажарилган | M42: Январ | N42: Мажмуалар | O42: =+O41+1 -> 40 | P42: =+O42-A42 -> 0 | T42: =+J42 -> 0
A43: 41 | B43: 44922 | C43: Мажмуа ва ташкилотлар билан муаммоли масалалар юзасидан йиғилиш | D43: Вилоятда дастурловчи мутахассисларни жалб қилиб, вилоятда IT-технологияларни жалб этиш, барча соҳаларни рақамлаштириш масалаларини мувофиқлаштирувчи штаб ташкил этиш Тошкент шаҳрида ташкил этилган “Халқ назорати” электрон платформаси фаолиятини кўриб чиқиб, ушбу дастурни вилоятда жорий этиш. | E43: 44957 | G43: Вилоят Ахборот технологиялари ва коммуникацияларини ривожлантириш бошқармаси (С.Шаймардонов), вилоят ҳокимлиги ҳузуридаги “Ахборот-коммуникация технологияларини ривожлантириш маркази” давлат унитар корхонаси (Ж.Менглиев) | H43: А.Амиров | I43: Бажарилган | M43: Январ | N43: Мажмуалар | O43: =+O42+1 -> 41 | P43: =+O43-A43 -> 0 | T43: =+J43 -> 0
A44: 42 | B44: 44922 | C44: Мажмуа ва ташкилотлар билан муаммоли масалалар юзасидан йиғилиш | D44: Вилоятда энергия манбаларидан оқилона фойдаланиш бўйича доимий назорат ўрнатиш, аниқланган қонунбузилиш ҳолатлари бартарф этиш чораларини белгилаш. | E44: 45080 | F44: Доимий | G44: “Ўздавэнергоназорат” инспекцияси Сурхондарё ҳудудий бўлими (Ядгаров), “Ўздавнефтгазинспекцияси” Сурхондарё ҳудудий бўлими (Муҳаммадиев) | H44: А.Амиров | I44: Бажарилган | J44: 05.04.2023 йил ҳолатига 98 холатларда 256 972 минг квт соат ёки 2 млрд 31 милл сўлик ноқуний уланиш ва энергия ресурсларини талон тарож қилинган. | M44: Январ | N44: Мажмуалар | O44: =+O43+1 -> 42 | P44: =+O44-A44 -> 0 | T44: =+J44 -> 05.04.2023 йил ҳолатига 98 холатларда 256 972 минг квт соат ёки 2 млрд 31 милл сўлик ноқуний уланиш ва энергия ресурсларини талон тарож қилинган.
A45: 43 | B45: 44922 | C45: Мажмуа ва ташкилотлар билан муаммоли масалалар юзасидан йиғилиш | D45: Президент таълим мактаблари қурилиши таъмирлаш ишларини жадаллаштириш; Термиз шаҳридаги 642 ўринли мактаб қурилишини учун тегишли ҳужжатларни (лойиҳа, экспертиза ва хоқазо) якунлаш, қўрилиш ишларини бошлаш. | E45: 44986 | F45: Билдирги | G45: Вилоят ҳокимининг ўринбосари А.Хидиров, Ягона буюртмачи инжинеринг компанияси (А.Арамов) | H45: А.Амиров | I45: Бажарилган | M45: Январ | N45: Мажмуалар | O45: =+O44+1 -> 43 | P45: =+O45-A45 -> 0 | T45: =+J45 -> 0
A46: 44 | B46: 44922 | C46: Мажмуа ва ташкилотлар билан муаммоли масалалар юзасидан йиғилиш | D46: Сариосиё тумани тиббиёт бирлашмасида электр таъминотини яхшилаш чора-тадбирларини белгилаш. | E46: 44925 | G46: Ҳудудий электр тармоқлари корхонаси (М.Шамсиддинов) Сариосиё тумани ҳокимлиги | H46: А.Амиров | I46: Бажарилган | M46: Январ | N46: Мажмуалар | O46: =+O45+1 -> 44 | P46: =+O46-A46 -> 0 | T46: =+J46 -> 0
A47: 45 | B47: 44922 | C47: Мажмуа ва ташкилотлар билан муаммоли масалалар юзасидан йиғилиш | D47: “Алпомиш” кураш мажмуасини реконструкция қилиш бўйича таклиф ишлаб чиқиш. | E47: 44925 | G47: Ягона буюртмаси инжинеринг компанияси (А.Арамов), Қурилиш бош бошқармаси (К.Эшматов) | H47: А.Амиров | I47: Бажарилган | M47: Январ | N47: Мажмуалар | O47: =+O46+1 -> 45 | P47: =+O47-A47 -> 0 | T47: =+J47 -> 0
A48: 46 | B48: 44922 | C48: Мажмуа ва ташкилотлар билан муаммоли масалалар юзасидан йиғилиш | D48: Сариосиё тумани Сангардак шаршараси ҳудудида сайёҳлар учун қулай шароит яратиш учун ҳорижий валюта маблағларини алмаштириш шаҳобчаси ташкил этиш, автомобиллар учун қўшимча турар жойларни кенгатириш. | E48: 45111 | G48: Сариосиё туман хокимлиги, “Сурхондарёавтойўл” ҳудудий йўллардан фойдаланиш ташкилоти (М.Алламурадов) | H48: А.Амиров | I48: Бажарилган | J48: Сайёҳлар учун қулай шароит яратиш учун ҳорижий валюта маблағларини алмаштириш шаҳобчаси ташкил этилди. | M48: Январ | N48: Мажмуалар | O48: =+O47+1 -> 46 | P48: =+O48-A48 -> 0 | Q48: 45066 | T48: =+J48 -> Сайёҳлар учун қулай шароит яратиш учун ҳорижий валюта маблағларини алмаштириш шаҳобчаси ташкил этилди.
A49: 47 | B49: 44922 | C49: Мажмуа ва ташкилотлар билан муаммоли масалалар юзасидан йиғилиш | D49: Термиз шаҳридаги болалар ва истироҳат боғлари таъмирлаш ва реконструкция қилиш бўйича таклиф ишлаб чиқиш. | E49: 44925 | G49: Термиз шаҳар ҳокими Ў.Тўраев | H49: А.Амиров | I49: Бажарилган | M49: Январ | N49: Мажмуалар | O49: =+O48+1 -> 47 | P49: =+O49-A49 -> 0 | T49: =+J49 -> 0
A50: 48 | B50: 44923 | C50: Термиз шаҳри | D50: Термиз шаҳри “Болажон” боғи ҳудудидаги йўлни таъмирлаш ишларини якунлаш ва вилоят ҳокимига ахборот бериш | E50: 44931 | G50: “Сурхондарёавтойўл” ҳудудий йўллардан фойдаланиш бошқармаси (Қиличев) | H50: А.Амиров | I50: Бажарилган | M50: Январ | N50: Мажмуалар | O50: =+O49+1 -> 48 | P50: =+O50-A50 -> 0 | T50: =+J50 -> 0
A51: 49 | B51: 44923 | C51: Термиз шаҳри | D51: Куз-қиш мавсумини беталофат ўтказиш бўйича тузилган вилоят штабининг кунлик ахборотини вилоят ҳокимига киритиб бориш. | E51: 44982 | F51: Доимий | G51: Виоят ҳокимининг ўринбосари А.Хидиров | H51: А.Амиров | I51: Бажарилган | M51: Январ | N51: Мажмуалар | O51: =+O50+1 -> 49 | P51: =+O51-A51 -> 0 | T51: =+J51 -> 0
A52: 50 | B52: 44923 | C52: Бандихон тумани | D52: Бандихон тумани “Бектепа” маҳалласидаги қурилиши тугалланмаган давлат мактабгача таълим ташкилотининг қурилишини якунлаб, фойдаланишга топшириш. | E52: 45010 | F52: Билдирги | G52: Вилоят ҳокимининг ўринбосари А.Хидиров, Бандихон тумани ҳокими, Қурилиш бошқармаси қурилиш назорати мутахассислари | H52: А.Амиров | I52: Бажарилган | M52: Январ | N52: Мажмуалар | O52: =+O51+1 -> 50 | P52: =+O52-A52 -> 0
A53: 51 | B53: 44923 | C53: Бандихон тумани | D53: Бандихон тумани “Наврўз” маҳалласига янги трансформатор ўрнатиш. Фуқаронинг телефон рақами 998975528821 | E53: 44958 | G53: Вилоят хокимлиги мурожаатлар бўлим мудири Б.Дониёров | H53: Б.Дониёров | I53: Бажарилган | M53: Январ | N53: Мажмуалар | O53: =+O52+1 -> 51 | P53: =+O53-A53 -> 0 | T53: =+J53 -> 0
A54: 52 | B54: 44923 | C54: Қизириқ тумани | D54: Қизириқ тумани марказий деҳқон бозорини ободонлаштириш, устунларни таъмирлаш, аликафон қопламаларини алмаштириш, бетонлаш, кўприкни таъмирлаш, расталарни тартибга келтириш, йўлларни, пиёдалар ўтиш йўлагини таъмирлаш ишларини бажариш. | E54: 44977 | F54: Билдирги | G54: Қизириқ тумани ҳокими | H54: Қизириқ тумани | I54: Бажарилган | M54: Январ | N54: туманлар | O54: =+O53+1 -> 52 | P54: =+O54-A54 -> 0 | T54: =+J54 -> 0
A55: 53 | B55: 44923 | C55: Қизириқ тумани | D55: Қизириқ туман тиббиёт бирлашмасининг янгидан қурилаётган қўшимча биноси қурилишини якунлаш, жихозлаш ва фойдаланишга топшириш | E55: 44977 | F55: Билдирги | G55: Қизириқ тумани ҳокими | H55: Қизириқ тумани | I55: Бажарилган | M55: Январ | N55: туманлар | O55: =+O54+1 -> 53 | P55: =+O55-A55 -> 0 | T55: =+J55 -> 0
A56: 54 | B56: 44923 | C56: Термиз шаҳри | D56: Термиз шаҳри Фаровон массивидаги кўп қаватли уйлар қурилиши учун ер майдонлари ажратиш қарорлари ва бошқа ҳужжатларни тўлиқ ўрганиб чиқиш | E56: 44931 | G56: Вилоят ҳокимининг ўринбосари А.Хидиров, Қурилиш бошқармаси (Эшматов) | H56: А.Амиров | I56: Бажарилган | M56: Январ | N56: Мажмуалар | O56: =+O55+1 -> 54 | P56: =+O56-A56 -> 0 | T56: =+J56 -> 0
A57: 55 | B57: 44923 | C57: Термиз шаҳри | D57: Термиз шаҳар сектор раҳбарлари томонидан ҳар бир сектор ҳудудида 1 тадан маҳаллани намунали ҳудудга айлантириш бўйича “Ўзбекистон” маҳалласи биносида тақдимот ўтказиш. | E57: 44931 | G57: Термиз шаҳар сектор раҳбарлари | H57: Термиз шаҳар | I57: Бажарилган | M57: Январ | N57: туманлар | O57: =+O56+1 -> 55 | P57: =+O57-A57 -> 0 | T57: =+J57 -> 0
A58: 56 | B58: 44923 | C58: Термиз шаҳри | D58: Термиз шаҳридаги бекатлар, жамоат транспортининг ҳолати бўйича Термиз шаҳри “Ўзбекистон” маҳалласи биносида тақдимот ўтказиш | E58: 44931 | G58: Транспорт бошқармаси (И.Ибрагимов). | H58: А.Амиров | I58: Бажарилган | M58: Январ | N58: Мажмуалар | O58: =+O57+1 -> 56 | P58: =+O58-A58 -> 0 | T58: =+J58 -> 0
A59: 57 | B59: 44923 | C59: Термиз шаҳри | D59: Термиз шаҳрида чиқиндиларни йиғиш, олиб чиқиш ва тозалик ишлари янги босқичга олиб чиқиш бўйича тақдимот ўтказиш | E59: 44925 | G59: Термиз шаҳар ҳокимлиги (Тўраев), “Био Техно Эко” МЧЖ (Боқижонов) | H59: Термиз шаҳар | I59: Бажарилган | M59: Январ | N59: туманлар | O59: =+O58+1 -> 57 | P59: =+O59-A59 -> 0 | T59: =+J59 -> 0
A60: 58 | B60: 44924 | C60: Музработ тумани | D60: Музработ ва Қизириқ туманлари давлат аҳамиятидаги йўлларини таъмирлаш чораларини кўриш (йўлларни кесиш орқали таъмирлаш ишларини амалга ошириш). | E60: 45078 | G60: “Сурхондарёавтойўл” ҳудудий йўллардан фойдаланиш ташкилоти (У.Темиров) | H60: А.Амиров | I60: Бажарилган | M60: Январ | N60: Мажмуалар | O60: =+O59+1 -> 58 | P60: =+O60-A60 -> 0 | Q60: 45066 | T60: =+J60 -> 0 | V60: 58 band boʻyicha Qiziriq tumanidagi avtomobil yoʻllarini tamirlash ishlari davom etmoqda
A61: 59 | B61: 44924 | C61: Термиз тумани | D61: Қорабайир отлари маҳорат мактабида ободонлаштириш ишларини амалга ошириш, Ўзбекистон Республикаси Бош вазири А.Арипов ташрифига тайёрлаш. | E61: 44931 | G61: Вилоят ҳокимининг ўринбосари А.Хидиров, Миллий гвардия бошқармаси (Саидов) | H61: А.Амиров | I61: Бажарилган | M61: Январ | N61: Мажмуалар | O61: =+O60+1 -> 59 | P61: =+O61-A61 -> 0 | T61: =+J61 -> 0
A62: 60 | B62: 44925 | C62: Денов тумани | D62: Денов туманидаги “Денов Дендрарий боғи” ва ҳокимлик биноси атрофидаги ноқонуний тартибда олиб борилаётган қурилиш ишларини тартибга солиш чораларини кўриш. | E62: 44931 | G62: Қурилиш бош бошқармаси (Эшматов) | H62: А.Амиров | I62: Бажарилган | M62: Январ | N62: Мажмуалар | O62: =+O61+1 -> 60 | P62: =+O62-A62 -> 0 | T62: =+J62 -> 0
A63: 61 | B63: 44925 | C63: Денов тумани | D63: Денов тумандаги “Чим” маҳалласига оптик толали интернет тармоғи тортиш. | E63: 44986 | G63: Ахборот техналогиялари ва коммуникацияларини ривожлантириш бошқармаси бошлиғи (Шаймарданов), “Узбектелеком” АК вилоят филиали (Норқўчқоров) | H63: А.Амиров | I63: Бажарилган | M63: Январ | N63: Мажмуалар | O63: =+O62+1 -> 61 | P63: =+O63-A63 -> 0 | T63: =+J63 -> 0
A64: 62 | B64: 44925 | C64: Денов тумани | D64: Денов туманида энергия тежовчи ускуналарни ўрнатиш бўйича 2 та маҳаллада намунавий эко маҳаллалар ташкил этиш. | E64: 44977 | G64: Вилоят ҳокимининг ўринбосари А.Хидиров Денов тумани ҳокимлиги (Алламуродов) | H64: А.Амиров | I64: Бажарилган | M64: Январ | N64: Мажмуалар | O64: =+O63+1 -> 62 | P64: =+O64-A64 -> 0 | T64: =+J64 -> 0
A65: 63 | B65: 44925 | C65: Денов тумани | D65: Денов туманидаги эски бозор ҳудудида амалга оширилаётган ишлар ва туманнинг космплекс ижтимоий-иқтисодий ривожлантириш борасида амалга ошириладиган лойиҳалар бўйича тақдимот қилиш | E65: 44977 | F65: Билдирги | G65: Вилоят ҳокимининг тармоқлар бўйича ўринбосарлари, Денов тумани ҳокими А.Алламуродов | H65: А.Амиров | I65: Бажарилган | M65: Январ | N65: Мажмуалар | O65: =+O64+1 -> 63 | P65: =+O65-A65 -> 0 | T65: =+J65 -> 0
A66: 64 | B66: 44925 | C66: Термиз шаҳри | D66: Аёлларни реабилитация қилиш ва мослаштириш маркази учун шароитга эга бинога кўчириш таклифини ишлаб чиқиш. | E66: 45021 | F66: Билдирги | G66: Вилоят ҳокимининг ўринбосарлари З.Хидирова, Термиз шаҳар ҳокими Ў.Тўраев. | H66: З.Хидирова | I66: Бажарилган | M66: Январ | N66: Мажмуалар | O66: =+O65+1 -> 64 | P66: =+O66-A66 -> 0
A67: 65 | B67: 44925 | C67: Термиз шаҳри | D67: Термиз шаҳридаги собиқ 12-сонли Меҳрибонлик уйи ўрнида ташкил этилиши белгиланган ихтисослаштирилган мактаб интернатига қўшимча бино қуриш ишларини якунлаган ҳолда мактаб фаолиятини бошлаш. | E67: 45017 | F67: Билдирги | G67: Вилоят ҳокимининг ўринбосарлари А.Хидиров, И.Сапаров. | H67: А.Амиров | I67: Бажарилган | M67: Январ | N67: Мажмуалар | O67: =+O66+1 -> 65 | P67: =+O67-A67 -> 0 | T67: =+J67 -> 0
A68: 66 | B68: 44925 | D68: Жорий йил январь ойи охирига қадар биомаҳсулотлар ишлаб чиқариш мақсадида биофабрика қуриш. | E68: 45000 | F68: Билдирги | G68: Вилоят ҳокимининг ўринбосарлари , Ф.Исмоилов | H68: Ф.Исмоилов | I68: Бажарилган | M68: Январ | N68: Мажмуалар | O68: =+O67+1 -> 66 | P68: =+O68-A68 -> 0
A69: 67 | B69: 44925 | C69: Шеробод тумани Зарабоғ қишлоғи | D69: Шеробод тумани "Зарабоғ" маҳалласи Зарабоғ қишлоғида аҳоли томонидан хашар йўли билан қурилган кўприкни бетонлаш. | E69: 44929 | G69: Вилоят ҳокимининг ўринбосари А.Хидиров, Сурхондарёкўприкқурилиш МЧЖ | H69: А.Амиров | I69: Бажарилган | M69: Январ | N69: Мажмуалар | O69: =+O68+1 -> 67 | P69: =+O69-A69 -> 0 | T69: =+J69 -> 0
A70: 68 | B70: 44925 | C70: Шеробод тумани Зарабоғ қишлоғи | D70: Шеробод тумани "Зарабоғ" маҳалласига борувчи йўлларни кесиб таъмирлаш ишларини амалга ошириш. (Натижасини мфй раиси Аминов Оромиддиндан 99-673-41-63 сўраш) | E70: 45087 | G70: “Сурхондарёавтойўл” (У.Темиров). | H70: А.Амиров | I70: Бажарилган | M70: Январ | N70: Мажмуалар | O70: =+O69+1 -> 68 | P70: =+O70-A70 -> 0 | Q70: 45066 | T70: Ишлар бошланиб, охирига етказилмаган. | V70: Бошланмаган
A71: 69 | B71: 44925 | C71: Шеробод тумани Зарабоғ қишлоғи | D71: Шеробод тумани "Пошхурт" ва "Зарабоғ" маҳалласига йўлларини тошлаш ва катоклаш ишларини амалга ошириш. | E71: 45066 | F71: Билдирги | G71: “Сурхондарёавтойўл” (У.Темиров). | H71: А.Амиров | I71: Бажарилган | M71: Январ | N71: Мажмуалар | O71: =+O70+1 -> 69 | P71: =+O71-A71 -> 0 | Q71: 45066 | R71: 45070 | T71: =+J71 -> 0
A72: 70 | B72: 44925 | C72: Шеробод тумани Зарабоғ қишлоғи | D72: Шеробод туманидаги шифохоналарга қуёш фотоэлектр панелларини ўрнатиш ишларини амалга ошириш. | E72: 45076 | F72: Билдирги | G72: Шеробод туман (З.Халилов) | H72: Шеробод тумани | I72: Бажарилган | M72: Январ | N72: туманлар | O72: =+O71+1 -> 70 | P72: =+O72-A72 -> 0 | T72: =+J72 -> 0
A73: 71 | B73: 44925 | D73: "Оравит керамикс" МЧЖни газ тармоғинига улаш ишларини амалга ошириш. | E73: 44932 | G73: “Hududgaz Surxondaryo” газ таъминоти филиали (М.Мансуров) | H73: А.Амиров | I73: Бажарилган | M73: Январ | N73: Мажмуалар | O73: =+O72+1 -> 71 | P73: =+O73-A73 -> 0 | T73: =+J73 -> 0
A74: 72 | B74: 44925 | C74: Мажмуа ва ташкилотлар билан муаммоли масалалар юзасидан йиғилиш | D74: Аҳолини тоза ичимлик суви билан таъминлаш лойиҳалари юзасидан тақдимот ташкил этиш ва объектларни Бош вазир ташрифига тайёрлаш. | E74: 44936 | G74: Вилоят ҳокимининг ўринбосари А.Хидиров, “Сурхондарё сув таъминоти” МЧЖ (Х.Сафаров) | H74: А.Амиров | I74: Бажарилган | M74: Январ | N74: Мажмуалар | O74: =+O73+1 -> 72 | P74: =+O74-A74 -> 0 | T74: =+J74 -> 0
A75: 73 | B75: 44925 | C75: Мажмуа ва ташкилотлар билан муаммоли масалалар юзасидан йиғилиш | D75: Термиз шаҳар кичик саноат зонасидаги ичимлик сувини текширувдан ўтказиш ва электр энергияси таъминотини яхшилаш. | E75: 44964 | F75: Билдирги | G75: “Сурхондарё ҳудудий электр тармоқлари корхонаси” АЖ (М.Шамсиддинов) | H75: А.Амиров | I75: Бажарилган | M75: Январ | N75: Мажмуалар | O75: =+O74+1 -> 73 | P75: =+O75-A75 -> 0 | T75: =+J75 -> 0
A76: 74 | B76: 44925 | D76: Қизириқ туманидаги 35-сонли мактабнинг қўшимча биносини таъмирлаш. | E76: 44941 | G76: Вилоят ҳокимнинг ўринбосари А.Хидиров Қизириқ тумани ҳокимлиги | H76: А.Амиров | I76: Бажарилган | M76: Январ | N76: Мажмуалар | O76: =+O75+1 -> 74 | P76: =+O76-A76 -> 0 | T76: =+J76 -> 0
A77: 75 | B77: 44925 | C77: Денов тумани | D77: Кейинги ҳафта Денов туманида камбағалликни қисқартириш ва аҳоли бандлигини таъминлаш бўйича қилинаётган ишлар билан танишув ташкил этиш. | E77: 44944 | G77: Вилоят ҳокимининг ўринбосарлари А.Хидиров, А.Орипов. вилоят ҳокимлиги котибият мудири (Б.Назаров). | H77: Ш.Жўраев | I77: Бажарилган | M77: Январ | N77: Мажмуалар | O77: =+O76+1 -> 75 | P77: =+O77-A77 -> 0 | T77: =+J77 -> 0
A78: 76 | B78: 44925 | D78: Термиз шаҳри “Жайхун” маҳалласи 45-уй 10-хонадонда яшовчи фуқаро Намозов Хўшбоқни (+99893-635-28-18) бандлигини таъминлаш масаласини ҳал этиш. | E78: 44958 | G78: Вилоят хокимлиги мурожаатлар бўлим мудири Б.Дониёров | H78: Б.Дониёров | I78: Бажарилган | M78: Январ | N78: Мажмуалар | O78: =+O77+1 -> 76 | P78: =+O78-A78 -> 0 | T78: =+J78 -> 0
A79: 77 | B79: 44925 | D79: Термиз шаҳри “Тупроққўрғон” маҳалласида яшовчи Эшалиева Ҳабибанинг (+99893-795-07-86) ногиронлик гуруҳига чиқариш масаласини ҳал этиш. | E79: 44958 | G79: Вилоят хокимлиги мурожаатлар бўлим мудири Б.Дониёров | H79: Б.Дониёров | I79: Бажарилган | M79: Январ | N79: Мажмуалар | O79: =+O78+1 -> 77 | P79: =+O79-A79 -> 0 | T79: =+J79 -> 0
A80: 78 | B80: 44922 | C80: Мажмуа ва ташкилотлар билан муаммоли масалалар юзасидан йиғилиш | D80: Вилоятдаги мавжуд муаммоли кредитлар ва уларни сўндириш бўйича туманларга тижорат банкларини бириктирган ҳолда кредит қарздорликларини сўндирилиши бўйича ишларни тизимли ташкил этиш. | E80: 44957 | G80: Марказий банки вилоят бош бошқармаси | H80: Ш.Ражабов | I80: Бажарилган | M80: Январ | N80: Мажмуалар | O80: =+O79+1 -> 78 | P80: =+O80-A80 -> 0 | T80: =+J80 -> 0
A81: 79 | B81: 44922 | C81: Мажмуа ва ташкилотлар билан муаммоли масалалар юзасидан йиғилиш | D81: Вилоятда “0” шаклда ҳисобот топширган кичик бизнес субъектлари фаолиятини ўрганиш, ишламаслик сабабларини ўрганиб, уларга амалий ёрдам кўрсатиш тизимини яратиш. | E81: 45078 | F81: доимий | G81: Вилоят Солиқ бошқармаси (Э.Нарманов) Термиз шаҳар, Ангор, Бандихон, Бойсун, Денов, Жарқўрғон, Қизириқ, Қумқўрғон, Музработ, Олтинсой, Сариосиё, Узун, Термиз, Шеробод, Шўрчи туман ҳокимликлари | H81: Шаҳар ва туман ҳокимликлари | I81: Бажарилган | J81: 2023 йил 27- апрел ҳолатига 603 та корхона томонидан 6 580 милл сўмлик товар айланмаси камайтириб кўрсатилган. Вилоят солиқ бошқармаси кейинги маълумотларни туманлар кесимида ҳам берсин. | M81: Январ | N81: туманлар | O81: =+O80+1 -> 79 | P81: =+O81-A81 -> 0 | T81: =+J81 -> 2023 йил 27- апрел ҳолатига 603 та корхона томонидан 6 580 милл сўмлик товар айланмаси камайтириб кўрсатилган. Вилоят солиқ бошқармаси кейинги маълумотларни туманлар кесимида ҳам берсин.
A82: 80 | B82: 44922 | C82: Мажмуа ва ташкилотлар билан муаммоли масалалар юзасидан йиғилиш | D82: Электрон имзо олмаган 8 минг та тадбиркорлик субъектларининг электрон имзо олишга амалий ёрдам кўрсатиш. | E82: 45078 | F82: Доимий | G82: Термиз шаҳри ва туманлар ҳокимликлари Солиқ Э.Нарманов-Амалий ёрдам кўрсатиш. | H82: Ш.Ражабов | I82: Бажарилган | J82: 2023 йил 27- апрел ҳолатига 8058 та кичик корхоналар мавжуд шундан 6750 таси (83,7%) Электрон имзо олинган. | M82: Январ | N82: Мажмуалар | O82: =+O81+1 -> 80 | P82: =+O82-A82 -> 0 | T82: =+J82 -> 2023 йил 27- апрел ҳолатига 8058 та кичик корхоналар мавжуд шундан 6750 таси (83,7%) Электрон имзо олинган.
A83: 81 | B83: 44922 | C83: Мажмуа ва ташкилотлар билан муаммоли масалалар юзасидан йиғилиш | D83: Вилоятда 2022 йил якуни бўйича макроиқтисодий кўрсаткичларнинг прогноз кўрсаткичлари ижросини таъминлаш. | E83: 44946 | G83: Вилоят Иқтисодий тараққиёт бошқармаси (Ш.Дўстмуродов), Термиз шаҳар ва туманлар ҳокимликлари | H83: Ш.Ражабов | I83: Бажарилган | M83: Январ | N83: Мажмуалар | O83: =+O82+1 -> 81 | P83: =+O83-A83 -> 0 | T83: =+J83 -> 0
A84: 82 | B84: 44922 | C84: Мажмуа ва ташкилотлар билан муаммоли масалалар юзасидан йиғилиш | D84: Солиқ тушумларини камайтирган корхоналар фаолиятини ўрганиб, уларнинг ишлаб чиқаришни кенгайтириш чоралари белгилаш. | E84: 44977 | G84: Термиз шаҳри ва туманлар ҳокимликлари, Вилоят Солиқ бошқармаси (Э.Нарманов) | H84: Ш.Ражабов | I84: Бажарилган | M84: Январ | N84: Мажмуалар | O84: =+O83+1 -> 82 | P84: =+O84-A84 -> 0 | T84: =+J84 -> 0
A85: 83 | B85: 44922 | C85: Мажмуа ва ташкилотлар билан муаммоли масалалар юзасидан йиғилиш | D85: Савдо саноат палатаси ҳамда Истеъмолчилар уюшмасига тадбирларни жалб қилиб, аъзолик бадалларини тўлашни ташкил этиш ҳамда иш ҳаққидан бўлган қарздорликларни ёпиш ҳамда барча туманларда штатларини ташкил этиш | E85: 45076 | F85: доимий | G85: Термиз шаҳри ва туманлар ҳокимликлари, Вилоят Савдо саноат палатаси, Истеъмолчилар уюшмаси (Р.Садуллаев тел 99-350-79-79) | H85: Ш.Ражабов | I85: Бажарилган | J85: Истемолчилар уюшмасига тўлов 56,6 фоизга бажарилган. Шўрчи, Музработ ва Бандихон тумианларида штатлар шакиллантирилмаган | M85: Январ | N85: Мажмуалар | O85: =+O84+1 -> 83 | P85: =+O85-A85 -> 0 | T85: =+J85 -> Истемолчилар уюшмасига тўлов 56,6 фоизга бажарилган. Шўрчи, Музработ ва Бандихон тумианларида штатлар шакиллантирилмаган
A86: 84 | B86: 44922 | C86: Мажмуа ва ташкилотлар билан муаммоли масалалар юзасидан йиғилиш | D86: Маҳалларда ишсизлар руйхатини шакллантириб, уларни иш билан таъминлаш чораларини белгилаш. Бунда, вилоятда фаолият юритиб келаётган бизнес субектларида қўшимча янги иш ўринларини яратиш чоралари белгилаш. | E86: 45077 | F86: Доимий | G86: Вилоят Камбағалликни қисқартириш ва Бандлик бош бошқармаси Маҳаллабай ишлаш ва тадбиркорликни ривожлантириш бошқармаси (Ш.Жўраев) Термиз шаҳри ва туманлар ҳокимликлари | H86: Ш.Ражабов | I86: Бажарилган | M86: Январ | N86: Мажмуалар | O86: =+O85+1 -> 84 | P86: =+O86-A86 -> 0 | T86: =+J86 -> 0
A87: 85 | B87: 44922 | C87: Мажмуа ва ташкилотлар билан муаммоли масалалар юзасидан йиғилиш | D87: Хотин-қизларни ижтимоий реестрига киритиш. | E87: 45076 | F87: Доимий | G87: Вилоят ҳокимининг ўринбосари З.Хидирова Термиз шаҳар ва туман ҳокимликлари. | H87: З.Хидирова | I87: Бажарилган | M87: Январ | N87: Мажмуалар | O87: =+O86+1 -> 85 | P87: =+O87-A87 -> 0 | T87: =+J87 -> 0
A88: 86 | B88: 44922 | C88: Мажмуа ва ташкилотлар билан муаммоли масалалар юзасидан йиғилиш | D88: "Оравит керамикс" МЧЖ томонидан фаолиятини кенгайтириш учун кредит маблағи ажратиш масаласини ҳал этиш. | E88: 44985 | G88: “Ўзсаноатқурилишбанк” АТБ Сурхондарё минтақавий филиали (Б.Арзиқулов) | H88: Ш.Ражабов | I88: Бажарилган | M88: Январ | N88: Мажмуалар | O88: =+O87+1 -> 86 | P88: =+O88-A88 -> 0 | T88: =+J88 -> 0
A89: 87 | B89: 44922 | C89: Мажмуа ва ташкилотлар билан муаммоли масалалар юзасидан йиғилиш | D89: Ёшларга кредит маблағлари ажратилмаганлиги бўйича тижорат банклари томонидан ҳисобот тақдим этиш. | E89: 45077 | F89: Доимий | G89: Марказий банк бош бошқармаси (А.Тўхтаев) | H89: Ш.Ражабов | I89: Бажарилган | J89: 11.05.2023 й ҳолатига 17 794 нафар ёшларга 238,6 млрд сўм миқдорида кредит маблағлари ажратилган. | M89: Январ | N89: Мажмуалар | O89: =+O88+1 -> 87 | P89: =+O89-A89 -> 0 | T89: =+J89 -> 11.05.2023 й ҳолатига 17 794 нафар ёшларга 238,6 млрд сўм миқдорида кредит маблағлари ажратилган.
A90: 88 | B90: 44922 | C90: Мажмуа ва ташкилотлар билан муаммоли масалалар юзасидан йиғилиш | D90: Вилоятда 11 та нодавлат мактабгача таълим ташкилотлари қуриш учун имтиёзли кредит олиб, қурилиш ишларини деярли бошламаган ташаббускорларининг кредит маблағларини қайтариш чораларини кўриш. | E90: 44991 | G90: Вилоят прокуратураси Марказий банк бош бошқармаси (А.Тўхтаев) | H90: Ш.Ражабов | I90: Бажарилган | M90: Январ | N90: Мажмуалар | O90: =+O89+1 -> 88 | P90: =+O90-A90 -> 0 | T90: =+J90 -> 0
A91: 89 | B91: 44928 | C91: Қизириқ тумани Истиқлол МФЙ | D91: Ҳудудларда ҳоким ёрдамчилари билан биргаликда "Аукцион" савдоларига чиқарилган ер майдонларини тўлиқ сотилишини таъминлаш чораларини кўриш. | E91: 45076 | F91: Доимий | G91: Маҳаллабай ишлаш ва тадбиркорликни ривожлантириш бошқармаси (Ш.Жўраев). | H91: Ш.Ражабов | I91: Бажарилган | J91: 03.04.2023 йил ҳолатига жами 2565 гектар ер майдондан 5294 та лотлар фуқаролар томонидан ютиб олинган. | M91: Январ | N91: Мажмуалар | O91: =+O90+1 -> 89 | P91: =+O91-A91 -> 0 | T91: =+J91 -> 03.04.2023 йил ҳолатига жами 2565 гектар ер майдондан 5294 та лотлар фуқаролар томонидан ютиб олинган.
A92: 90 | B92: 44928 | C92: Қизириқ тумани Истиқлол МФЙ | D92: Уй-жой сотиб олиш учун фуқароларга ажратилган субсидияларни ўзлаштирилишини таъминлаш. | E92: 45069 | G92: Марказий банк бош бошқармаси (А.Тўхтаев), Термиз шаҳар ва туман ҳокимликлари. | H92: Ш.Ражабов | I92: Бажарилган | J92: Вилоятда 2022 йилда уй-жой шароитларини яхшилашга муҳтож бўлган 1 308 нафар фуқароларга субсидия хабарномаси берилган бўлиб, шундан 805 нафар фуқароларга 214,9 млрд. сўм ипотека кредитлари ажратилган. Қолган фуқаролар 503 нафар | M92: Январ | N92: Мажмуалар | O92: =+O91+1 -> 90 | P92: =+O92-A92 -> 0 | T92: =+J92 -> Вилоятда 2022 йилда уй-жой шароитларини яхшилашга муҳтож бўлган 1 308 нафар фуқароларга субсидия хабарномаси берилган бўлиб, шундан 805 нафар фуқароларга 214,9 млрд. сўм ипотека кредитлари ажратилган. Қолган фуқаролар 503 нафар
A93: 91 | B93: 44928 | C93: Қизириқ тумани Истиқлол МФЙ | D93: Хизмат кўрсатиш соҳасида янги лойиҳаларни ишга туширилишини таъминлаган ҳолда туну-кун фаолият кўрсатадиган кўчаларда: -кўчма савдо объектлари фаолиятини ташкил этиш; -йирик замонавий кўнгилочар хизмат кўрсатиш объектларини ишга туширилишини таъминлаш. | E93: 45078 | F93: Доимий | G93: Иқтисодий тараққиёт ва камбағалликни қисқартириш бош бошқармаси (Ш.Дўстмуратов), Давлат солиқ бошқармаси (Э.Нарманов), Термиз шаҳар ва туман ҳокимликлари. | H93: Ш.Ражабов | I93: Бажарилган | J93: 26.04.2023 йил ҳолатига. 2023 йилда 831 та кўчма савдо жойлари онлайин савдога чиқарилди. | M93: Январ | N93: Мажмуалар | O93: =+O92+1 -> 91 | P93: =+O93-A93 -> 0 | T93: =+J93 -> 26.04.2023 йил ҳолатига. 2023 йилда 831 та кўчма савдо жойлари онлайин савдога чиқарилди.
A94: 92 | B94: 44928 | C94: Қизириқ тумани Истиқлол МФЙ | D94: Вилоятда 2022 йилда 3 та дафтарда турадиган ва ишсиз фуқароларга "Е-АУКЦИОН" платформаси орқали ажратилган ер майдонлари талабгорларини деҳқон хўжаликлари сифатида рўйхатдан ўтишлари ёки ўзини-ўзи банд қилиш ишларини ташкиллаштириш ҳамда натижаси бўйича вилоят ҳокими раҳбарлигида муҳокама ўтказиб бориш. | E94: 45076 | F94: Доимий | G94: Маҳаллабай ишлаш ва тадбиркорликни ривожлантириш бошқармаси (Ш.Жўраев), Термиз шаҳар ва туман сектор раҳбарлари. | H94: Ш.Ражабов | I94: Бажарилган | J94: 03.04.2023 йил ҳолатига жами 2565 гектар ер майдондан 5294 та лотлар фуқаролар томонидан ютиб олинган. Шундан, 622 гектар 1 444 нафар дафтарда турган фуқаролар ва мигрантларга ажратилди. | M94: Январ | N94: Мажмуалар | O94: =+O93+1 -> 92 | P94: =+O94-A94 -> 0 | T94: =+J94 -> 03.04.2023 йил ҳолатига жами 2565 гектар ер майдондан 5294 та лотлар фуқаролар томонидан ютиб олинган. Шундан, 622 гектар 1 444 нафар дафтарда турган фуқаролар ва мигрантларга ажратилди.
A95: 93 | B95: 44928 | C95: Қизириқ тумани Истиқлол МФЙ | D95: Ҳар бир маҳаллада ойига камида 2 тадан кичик лойиҳаларни шакллантириб, ишга тушириш чораларини кўриш. | E95: 45076 | F95: Доимий | G95: Маҳаллабай ишлаш ва тадбиркорликни ривожлантириш бошқармаси (Ш.Жўраев), Термиз шаҳар ва туман сектор раҳбарлари. | H95: Ш.Ражабов | I95: Бажарилган | J95: 01.03.2023 йил ҳолатига 1 300 та лойиҳалар амалга оширилган | M95: Январ | N95: Мажмуалар | O95: =+O94+1 -> 93 | P95: =+O95-A95 -> 0 | T95: =+J95 -> 01.03.2023 йил ҳолатига 1 300 та лойиҳалар амалга оширилган
A96: 94 | B96: 44928 | C96: Қизириқ тумани Истиқлол МФЙ | D96: Маҳалла раислари, ҳоким ёрдамчилари, ёшлар етакчилари ва хотин-қизлар фаоллари билан биргаликда маҳаллалардаги ижтимоий ҳимоя реестрига киритилган ҳонадонларнинг хатловини якунлаш. | E96: 44949 | G96: Маҳаллабай ишлаш ва тадбиркорликни ривожлантириш бошқармаси (Ш.Жўраев), Ёшлар ишлари агентлиги (Ж.Чориев), Маҳалла ва нуронийларни қўллаб-қувватлаш бошқармаси (Ф.Таиров) Термиз шаҳар ва туман сектор раҳбарлари. | H96: Ш.Ражабов | I96: Бажарилган | M96: Январ | N96: Мажмуалар | O96: =+O95+1 -> 94 | P96: =+O96-A96 -> 0 | T96: =+J96 -> 0
A97: 95 | B97: 44928 | D97: Вилоят тиббий-ижтимоий хизматларни ривожлантириш бошқармасининг 2022 йилда ногиронларга етказиб берилган воситалар учун мавжуд бўлган қарздорлик бўйича таклиф тайёрлаш. | E97: 44951 | G97: Вилоят Молия бошқармаси (Ж.Нормуминов) | H97: Ш.Ражабов | I97: Бажарилган | M97: Январ | N97: Мажмуалар | O97: =+O96+1 -> 95 | P97: =+O97-A97 -> 0 | T97: =+J97 -> 0
A98: 96 | B98: 44928 | D98: Термиз Санъат саройидаги Амфитеатр биносини таъмирлаш учун 300 млн сўм маблағ ажратиш. | E98: 44972 | G98: Молия бош бошқармаси (Ж.Нормуминов). | H98: Ш.Ражабов | I98: Бажарилган | M98: Январ | N98: Мажмуалар | O98: =+O97+1 -> 96 | P98: =+O98-A98 -> 0 | T98: =+J98 -> 0
A99: 97 | B99: 44928 | D99: Уй-жойга мухтож хотин - қизлар учун ажратилиши белгиланган арзон уй-жойлар учун ипотека кредитлари ажратилишини таъминлаш. | E99: 45024 | F99: Билдирги | G99: Марказий банк бош бошқармаси (А.Тўхтаев). | H99: Ш.Ражабов | I99: Бажарилган | J99: Халқ банкида 2 нфар фуқарога ҳужжатлар расмийлаштирилмасдан қолган | M99: Январ | N99: Мажмуалар | O99: =+O98+1 -> 97 | P99: =+O99-A99 -> 0 | T99: =+J99 -> Халқ банкида 2 нфар фуқарога ҳужжатлар расмийлаштирилмасдан қолган
A100: 98 | B100: 44933 | C100: Талабалар билан учрашув | D100: Мустақиллик байрами тадбирлари учун олинган либослар учун қопланмай қолган 266 млн сўм қарздорликни тўлаб бериш бўйича таклиф киритиш. (Зиёдуллаева Феруза 91-239-77-75) | E100: 44958 | G100: Молия бош бошқармаси (Ж.Нормуминов). | H100: Ш.Ражабов | I100: Бажарилган | M100: Январ | N100: Мажмуалар | O100: =+O99+1 -> 98 | P100: =+O100-A100 -> 0 | T100: =+J100 -> 0
...

Sheet Свод умумий-2
A1: Вилоят ҳокими У.Қосимов томонидан ҳудудларни ўрганиш давомида аниқланган муаммоларни бартараф этиш бўйича берилаётган тезкор топшириқларнинг ижроси тўғрисида МАЪЛУМОТ
I2: =+E7+F7 -> 188
E4: 10.11.2025 йил ҳолатига
A5: Т\Р | B5: Масъуллар | C5: Жами топшириқ сони | D5: Шундан
D6: Бажарилган | E6: Бажарилмаган | F6: Бажарилмоқда | V6: Бажарилган | W6: Бажарилмаган | X6: Бажарилмоқда
A7: ЖАМИ | C7: =+C8+C27 -> 4929 | D7: =+D8+D27 -> 4741 | E7: =+E8+E27 -> 136 | F7: =+F8+F27 -> 52 | U7: =+A7 -> ЖАМИ | V7: =+D7/C7 -> 0.96185839 | W7: =+E7/C7 -> 0.027591804 | X7: =+F7/C7 -> 0.010549807
A8: ЖАМИ (Мажмуалар) | C8: =SUM(C9:C26) -> 3482 | D8: =SUM(D9:D26) -> 3370 | E8: =SUM(E9:E26) -> 68 | F8: =SUM(F9:F26) -> 44 | U8: =+A8 -> ЖАМИ (Мажмуалар) | V8: =+D8/C8 -> 0.96783458 | W8: =+E8/C8 -> 0.019529006 | X8: =+F8/C8 -> 0.012636416
A9: 1 | B9: Ш.Ражабов | C9: =+D9+E9+F9 -> 565 | D9: =+COUNTIFS('Жами топшириқлар-1'!$H$3:$H$5027,B9,'Жами топшириқлар-1'!$I$3:$I$5027,$D$6) -> 554 | E9: =+COUNTIFS('Жами топшириқлар-1'!$H$3:$H$5027,B9,'Жами топшириқлар-1'!$I$3:$I$5027,$E$6) -> 7 | F9: =+COUNTIFS('Жами топшириқлар-1'!$H$3:$H$5027,B9,'Жами топшириқлар-1'!$I$3:$I$5027,$F$6) -> 4 | I9: Иқтисод | T9: =+A9 -> 1 | U9: =+B9 -> Ш.Ражабов | V9: =+D9/C9 -> 0.98053097 | W9: =+E9/C9 -> 0.012389381 | X9: =+F9/C9 -> 0.007079646
A10: 2 | B10: А.Амиров | C10: =+D10+E10+F10 -> 972 | D10: =+COUNTIFS('Жами топшириқлар-1'!$H$3:$H$5027,B10,'Жами топшириқлар-1'!$I$3:$I$5027,$D$6) -> 927 | E10: =+COUNTIFS('Жами топшириқлар-1'!$H$3:$H$5027,B10,'Жами топшириқлар-1'!$I$3:$I$5027,$E$6) -> 20 | F10: =+COUNTIFS('Жами топшириқлар-1'!$H$3:$H$5027,B10,'Жами топшириқлар-1'!$I$3:$I$5027,$F$6) -> 25 | I10: Қурилиш | T10: =+A10 -> 2 | U10: =+B10 -> А.Амиров | V10: =+D10/C10 -> 0.9537037 | W10: =+E10/C10 -> 0.020576132 | X10: =+F10/C10 -> 0.025720165
A11: 3 | B11: Ш.Жўраев | C11: =+D11+E11+F11 -> 209 | D11: =+COUNTIFS('Жами топшириқлар-1'!$H$3:$H$5027,B11,'Жами топшириқлар-1'!$I$3:$I$5027,$D$6) -> 205 | E11: =+COUNTIFS('Жами топшириқлар-1'!$H$3:$H$5027,B11,'Жами топшириқлар-1'!$I$3:$I$5027,$E$6) -> 4 | F11: =+COUNTIFS('Жами топшириқлар-1'!$H$3:$H$5027,B11,'Жами топшириқлар-1'!$I$3:$I$5027,$F$6) -> 0 | I11: Инвестиция | T11: =+A11 -> 3 | U11: =+B11 -> Ш.Жўраев | V11: =+D11/C11 -> 0.98086124 | W11: =+E11/C11 -> 0.019138756 | X11: =+F11/C11 -> 0
A12: 4 | B12: Ф.Исмоилов | C12: =+D12+E12+F12 -> 386 | D12: =+COUNTIFS('Жами топшириқлар-1'!$H$3:$H$5027,B12,'Жами топшириқлар-1'!$I$3:$I$5027,$D$6) -> 382 | E12: =+COUNTIFS('Жами топшириқлар-1'!$H$3:$H$5027,B12,'Жами топшириқлар-1'!$I$3:$I$5027,$E$6) -> 2 | F12: =+COUNTIFS('Жами топшириқлар-1'!$H$3:$H$5027,B12,'Жами топшириқлар-1'!$I$3:$I$5027,$F$6) -> 2 | I12: Қишлоқ хўжалиги | T12: =+A12 -> 4 | U12: =+B12 -> Ф.Исмоилов | V12: =+D12/C12 -> 0.98963731 | W12: =+E12/C12 -> 0.0051813472 | X12: =+F12/C12 -> 0.0051813472
A13: 5 | B13: И.Сапаров | C13: =+D13+E13+F13 -> 628 | D13: =+COUNTIFS('Жами топшириқлар-1'!$H$3:$H$5027,B13,'Жами топшириқлар-1'!$I$3:$I$5027,$D$6) -> 599 | E13: =+COUNTIFS('Жами топшириқлар-1'!$H$3:$H$5027,B13,'Жами топшириқлар-1'!$I$3:$I$5027,$E$6) -> 22 | F13: =+COUNTIFS('Жами топшириқлар-1'!$H$3:$H$5027,B13,'Жами топшириқлар-1'!$I$3:$I$5027,$F$6) -> 7 | I13: Ёшлар ва ижтимоий | T13: =+A13 -> 5 | U13: =+B13 -> И.Сапаров | V13: =+D13/C13 -> 0.95382166 | W13: =+E13/C13 -> 0.035031847 | X13: =+F13/C13 -> 0.011146497
A14: 6 | B14: Ж.Тўраев | C14: =+D14+E14+F14 -> 183 | D14: =+COUNTIFS('Жами топшириқлар-1'!$H$3:$H$5027,B14,'Жами топшириқлар-1'!$I$3:$I$5027,$D$6) -> 172 | E14: =+COUNTIFS('Жами топшириқлар-1'!$H$3:$H$5027,B14,'Жами топшириқлар-1'!$I$3:$I$5027,$E$6) -> 10 | F14: =+COUNTIFS('Жами топшириқлар-1'!$H$3:$H$5027,B14,'Жами топшириқлар-1'!$I$3:$I$5027,$F$6) -> 1 | I14: Туризм ва спорт | T14: =+A14 -> 6 | U14: =+B14 -> Ж.Тўраев | V14: =+D14/C14 -> 0.93989071 | W14: =+E14/C14 -> 0.054644809 | X14: =+F14/C14 -> 0.0054644809
A15: 7 | B15: А.Абдурахмонов | C15: =+D15+E15+F15 -> 14 | D15: =+COUNTIFS('Жами топшириқлар-1'!$H$3:$H$5027,B15,'Жами топшириқлар-1'!$I$3:$I$5027,$D$6) -> 14 | E15: =+COUNTIFS('Жами топшириқлар-1'!$H$3:$H$5027,B15,'Жами топшириқлар-1'!$I$3:$I$5027,$E$6) -> 0 | F15: =+COUNTIFS('Жами топшириқлар-1'!$H$3:$H$5027,B15,'Жами топшириқлар-1'!$I$3:$I$5027,$F$6) -> 0 | I15: Жамоат ва диний | T15: =+A15 -> 7 | U15: =+B15 -> А.Абдурахмонов | V15: =+D15/C15 -> 1 | W15: =+E15/C15 -> 0 | X15: =+F15/C15 -> 0
A16: 8 | B16: З.Хидирова | C16: =+D16+E16+F16 -> 55 | D16: =+COUNTIFS('Жами топшириқлар-1'!$H$3:$H$5027,B16,'Жами топшириқлар-1'!$I$3:$I$5027,$D$6) -> 54 | E16: =+COUNTIFS('Жами топшириқлар-1'!$H$3:$H$5027,B16,'Жами топшириқлар-1'!$I$3:$I$5027,$E$6) -> 1 | F16: =+COUNTIFS('Жами топшириқлар-1'!$H$3:$H$5027,B16,'Жами топшириқлар-1'!$I$3:$I$5027,$F$6) -> 0 | I16: Махалла ва оила | T16: =+A16 -> 8 | U16: =+B16 -> З.Хидирова | V16: =+D16/C16 -> 0.98181818 | W16: =+E16/C16 -> 0.018181818 | X16: =+F16/C16 -> 0
A17: 9 | B17: Ф.Менглиев | C17: =+D17+E17+F17 -> 171 | D17: =+COUNTIFS('Жами топшириқлар-1'!$H$3:$H$5027,B17,'Жами топшириқлар-1'!$I$3:$I$5027,$D$6) -> 171 | E17: =+COUNTIFS('Жами топшириқлар-1'!$H$3:$H$5027,B17,'Жами топшириқлар-1'!$I$3:$I$5027,$E$6) -> 0 | F17: =+COUNTIFS('Жами топшириқлар-1'!$H$3:$H$5027,B17,'Жами топшириқлар-1'!$I$3:$I$5027,$F$6) -> 0 | I17: Вил Кадр | T17: =+A17 -> 9 | U17: =+B17 -> Ф.Менглиев | V17: =+D17/C17 -> 1 | W17: =+E17/C17 -> 0 | X17: =+F17/C17 -> 0
A18: 10 | B18: Ф.Очилдиев | C18: =+D18+E18+F18 -> 10 | D18: =+COUNTIFS('Жами топшириқлар-1'!$H$3:$H$5027,B18,'Жами топшириқлар-1'!$I$3:$I$5027,$D$6) -> 9 | E18: =+COUNTIFS('Жами топшириқлар-1'!$H$3:$H$5027,B18,'Жами топшириқлар-1'!$I$3:$I$5027,$E$6) -> 0 | F18: =+COUNTIFS('Жами топшириқлар-1'!$H$3:$H$5027,B18,'Жами топшириқлар-1'!$I$3:$I$5027,$F$6) -> 1 | I18: Ахборот тахлил | T18: =+A18 -> 10 | U18: =+B18 -> Ф.Очилдиев | V18: =+D18/C18 -> 0.9 | W18: =+E18/C18 -> 0 | X18: =+F18/C18 -> 0.1
A19: 11 | B19: З.Назаров | C19: =+D19+E19+F19 -> 186 | D19: =+COUNTIFS('Жами топшириқлар-1'!$H$3:$H$5027,B19,'Жами топшириқлар-1'!$I$3:$I$5027,$D$6) -> 184 | E19: =+COUNTIFS('Жами топшириқлар-1'!$H$3:$H$5027,B19,'Жами топшириқлар-1'!$I$3:$I$5027,$E$6) -> 2 | F19: =+COUNTIFS('Жами топшириқлар-1'!$H$3:$H$5027,B19,'Жами топшириқлар-1'!$I$3:$I$5027,$F$6) -> 0 | I19: Харбий гурух | T19: =+A19 -> 11 | U19: =+B19 -> З.Назаров | V19: =+D19/C19 -> 0.98924731 | W19: =+E19/C19 -> 0.010752688 | X19: =+F19/C19 -> 0
A20: 12 | B20: О.Ашуров | C20: =+D20+E20+F20 -> 9 | D20: =+COUNTIFS('Жами топшириқлар-1'!$H$3:$H$5027,B20,'Жами топшириқлар-1'!$I$3:$I$5027,$D$6) -> 9 | E20: =+COUNTIFS('Жами топшириқлар-1'!$H$3:$H$5027,B20,'Жами топшириқлар-1'!$I$3:$I$5027,$E$6) -> 0 | F20: =+COUNTIFS('Жами топшириқлар-1'!$H$3:$H$5027,B20,'Жами топшириқлар-1'!$I$3:$I$5027,$F$6) -> 0 | T20: =+A20 -> 12 | U20: =+B20 -> О.Ашуров | V20: =+D20/C20 -> 1 | W20: =+E20/C20 -> 0 | X20: =+F20/C20 -> 0
A21: 13 | B21: М.Давлатов | C21: =+D21+E21+F21 -> 27 | D21: =+COUNTIFS('Жами топшириқлар-1'!$H$3:$H$5027,B21,'Жами топшириқлар-1'!$I$3:$I$5027,$D$6) -> 27 | E21: =+COUNTIFS('Жами топшириқлар-1'!$H$3:$H$5027,B21,'Жами топшириқлар-1'!$I$3:$I$5027,$E$6) -> 0 | F21: =+COUNTIFS('Жами топшириқлар-1'!$H$3:$H$5027,B21,'Жами топшириқлар-1'!$I$3:$I$5027,$F$6) -> 0 | T21: =+A21 -> 13 | U21: =+B21 -> М.Давлатов | V21: =+D21/C21 -> 1 | W21: =+E21/C21 -> 0 | X21: =+F21/C21 -> 0
A22: 14 | B22: Д.Бобоёров | C22: =+D22+E22+F22 -> 1 | D22: =+COUNTIFS('Жами топшириқлар-1'!$H$3:$H$5027,B22,'Жами топшириқлар-1'!$I$3:$I$5027,$D$6) -> 1 | E22: =+COUNTIFS('Жами топшириқлар-1'!$H$3:$H$5027,B22,'Жами топшириқлар-1'!$I$3:$I$5027,$E$6) -> 0 | F22: =+COUNTIFS('Жами топшириқлар-1'!$H$3:$H$5027,B22,'Жами топшириқлар-1'!$I$3:$I$5027,$F$6) -> 0 | T22: =+A22 -> 14 | U22: =+B22 -> Д.Бобоёров | V22: =+D22/C22 -> 1 | W22: =+E22/C22 -> 0 | X22: =+F22/C22 -> 0
A23: 15 | B23: Б.Дониёров | C23: =+D23+E23+F23 -> 66 | D23: =+COUNTIFS('Жами топшириқлар-1'!$H$3:$H$5027,B23,'Жами топшириқлар-1'!$I$3:$I$5027,$D$6) -> 62 | E23: =+COUNTIFS('Жами топшириқлар-1'!$H$3:$H$5027,B23,'Жами топшириқлар-1'!$I$3:$I$5027,$E$6) -> 0 | F23: =+COUNTIFS('Жами топшириқлар-1'!$H$3:$H$5027,B23,'Жами топшириқлар-1'!$I$3:$I$5027,$F$6) -> 4 | I23: Мурожаатлар | T23: =+A23 -> 15 | U23: =+B23 -> Б.Дониёров | V23: =+D23/C23 -> 0.93939394 | W23: =+E23/C23 -> 0 | X23: =+F23/C23 -> 0.060606061
A24: 16 | B24: Б.Бабаджанов Прокуратура (2-сектор) | C24: =+D24+E24+F24 -> 0 | D24: =+COUNTIFS('Жами топшириқлар-1'!$H$3:$H$5027,B24,'Жами топшириқлар-1'!$I$3:$I$5027,$D$6) -> 0 | E24: =+COUNTIFS('Жами топшириқлар-1'!$H$3:$H$5027,B24,'Жами топшириқлар-1'!$I$3:$I$5027,$E$6) -> 0 | F24: =+COUNTIFS('Жами топшириқлар-1'!$H$3:$H$5027,B24,'Жами топшириқлар-1'!$I$3:$I$5027,$F$6) -> 0 | I24: Вилоят, шаҳар ва туман прокурорлари | T24: =+A24 -> 16 | U24: =+B24 -> Б.Бабаджанов Прокуратура (2-сектор)
A25: 17 | B25: Т.Исмаилов ИИБ (3-сектор) | C25: =+D25+E25+F25 -> 0 | D25: =+COUNTIFS('Жами топшириқлар-1'!$H$3:$H$5027,B25,'Жами топшириқлар-1'!$I$3:$I$5027,$D$6) -> 0 | E25: =+COUNTIFS('Жами топшириқлар-1'!$H$3:$H$5027,B25,'Жами топшириқлар-1'!$I$3:$I$5027,$E$6) -> 0 | F25: =+COUNTIFS('Жами топшириқлар-1'!$H$3:$H$5027,B25,'Жами топшириқлар-1'!$I$3:$I$5027,$F$6) -> 0 | I25: Вилоят, шаҳар ва туман ИИБ бошлиқлари | T25: =+A25 -> 17 | U25: =+B25 -> Т.Исмаилов ИИБ (3-сектор)
A26: 18 | B26: Э.Нарманов Солиқ (4-сектор) | C26: =+D26+E26+F26 -> 0 | D26: =+COUNTIFS('Жами топшириқлар-1'!$H$3:$H$5027,B26,'Жами топшириқлар-1'!$I$3:$I$5027,$D$6) -> 0 | E26: =+COUNTIFS('Жами топшириқлар-1'!$H$3:$H$5027,B26,'Жами топшириқлар-1'!$I$3:$I$5027,$E$6) -> 0 | F26: =+COUNTIFS('Жами топшириқлар-1'!$H$3:$H$5027,B26,'Жами топшириқлар-1'!$I$3:$I$5027,$F$6) -> 0 | I26: Вилоят, шаҳар ва туман Солиқ бошлиқлари | T26: =+A26 -> 18 | U26: =+B26 -> Э.Нарманов Солиқ (4-сектор) | V26: =+D26/C26 -> #DIV/0! | W26: =+E26/C26 -> #DIV/0! | X26: =+F26/C26 -> #DIV/0!
A27: ЖАМИ (Туманлар) | C27: =SUM(C28:C43) -> 1447 | D27: =SUM(D28:D43) -> 1371 | E27: =SUM(E28:E43) -> 68 | F27: =SUM(F28:F43) -> 8 | U27: =+A27 -> ЖАМИ (Туманлар) | V27: =+D27/C27 -> 0.94747754 | W27: =+E27/C27 -> 0.04699378 | X27: =+F27/C27 -> 0.00552868
A28: 1 | B28: Термиз шаҳар | C28: =+D28+E28+F28 -> 286 | D28: =+COUNTIFS('Жами топшириқлар-1'!$H$3:$H$5027,B28,'Жами топшириқлар-1'!$I$3:$I$5027,$D$6) -> 277 | E28: =+COUNTIFS('Жами топшириқлар-1'!$H$3:$H$5027,B28,'Жами топшириқлар-1'!$I$3:$I$5027,$E$6) -> 6 | F28: =+COUNTIFS('Жами топшириқлар-1'!$H$3:$H$5027,B28,'Жами топшириқлар-1'!$I$3:$I$5027,$F$6) -> 3 | T28: =+A28 -> 1 | U28: =+B28 -> Термиз шаҳар | V28: =+D28/C28 -> 0.96853147 | W28: =+E28/C28 -> 0.020979021 | X28: =+F28/C28 -> 0.01048951
A29: 2 | B29: Ангор тумани | C29: =+D29+E29+F29 -> 75 | D29: =+COUNTIFS('Жами топшириқлар-1'!$H$3:$H$5027,B29,'Жами топшириқлар-1'!$I$3:$I$5027,$D$6) -> 66 | E29: =+COUNTIFS('Жами топшириқлар-1'!$H$3:$H$5027,B29,'Жами топшириқлар-1'!$I$3:$I$5027,$E$6) -> 8 | F29: =+COUNTIFS('Жами топшириқлар-1'!$H$3:$H$5027,B29,'Жами топшириқлар-1'!$I$3:$I$5027,$F$6) -> 1 | T29: =+A29 -> 2 | U29: =+B29 -> Ангор тумани | V29: =+D29/C29 -> 0.88 | W29: =+E29/C29 -> 0.10666667 | X29: =+F29/C29 -> 0.013333333
A30: 3 | B30: Бандихон тумани | C30: =+D30+E30+F30 -> 52 | D30: =+COUNTIFS('Жами топшириқлар-1'!$H$3:$H$5027,B30,'Жами топшириқлар-1'!$I$3:$I$5027,$D$6) -> 40 | E30: =+COUNTIFS('Жами топшириқлар-1'!$H$3:$H$5027,B30,'Жами топшириқлар-1'!$I$3:$I$5027,$E$6) -> 12 | F30: =+COUNTIFS('Жами топшириқлар-1'!$H$3:$H$5027,B30,'Жами топшириқлар-1'!$I$3:$I$5027,$F$6) -> 0 | T30: =+A30 -> 3 | U30: =+B30 -> Бандихон тумани | V30: =+D30/C30 -> 0.76923077 | W30: =+E30/C30 -> 0.23076923 | X30: =+F30/C30 -> 0
A31: 4 | B31: Бойсун тумани | C31: =+D31+E31+F31 -> 47 | D31: =+COUNTIFS('Жами топшириқлар-1'!$H$3:$H$5027,B31,'Жами топшириқлар-1'!$I$3:$I$5027,$D$6) -> 42 | E31: =+COUNTIFS('Жами топшириқлар-1'!$H$3:$H$5027,B31,'Жами топшириқлар-1'!$I$3:$I$5027,$E$6) -> 5 | F31: =+COUNTIFS('Жами топшириқлар-1'!$H$3:$H$5027,B31,'Жами топшириқлар-1'!$I$3:$I$5027,$F$6) -> 0 | T31: =+A31 -> 4 | U31: =+B31 -> Бойсун тумани | V31: =+D31/C31 -> 0.89361702 | W31: =+E31/C31 -> 0.10638298 | X31: =+F31/C31 -> 0
A32: 5 | B32: Денов тумани | C32: =+D32+E32+F32 -> 151 | D32: =+COUNTIFS('Жами топшириқлар-1'!$H$3:$H$5027,B32,'Жами топшириқлар-1'!$I$3:$I$5027,$D$6) -> 146 | E32: =+COUNTIFS('Жами топшириқлар-1'!$H$3:$H$5027,B32,'Жами топшириқлар-1'!$I$3:$I$5027,$E$6) -> 5 | F32: =+COUNTIFS('Жами топшириқлар-1'!$H$3:$H$5027,B32,'Жами топшириқлар-1'!$I$3:$I$5027,$F$6) -> 0 | T32: =+A32 -> 5 | U32: =+B32 -> Денов тумани | V32: =+D32/C32 -> 0.96688742 | W32: =+E32/C32 -> 0.033112583 | X32: =+F32/C32 -> 0
A33: 6 | B33: Жарқурғон тумани | C33: =+D33+E33+F33 -> 89 | D33: =+COUNTIFS('Жами топшириқлар-1'!$H$3:$H$5027,B33,'Жами топшириқлар-1'!$I$3:$I$5027,$D$6) -> 86 | E33: =+COUNTIFS('Жами топшириқлар-1'!$H$3:$H$5027,B33,'Жами топшириқлар-1'!$I$3:$I$5027,$E$6) -> 3 | F33: =+COUNTIFS('Жами топшириқлар-1'!$H$3:$H$5027,B33,'Жами топшириқлар-1'!$I$3:$I$5027,$F$6) -> 0 | T33: =+A33 -> 6 | U33: =+B33 -> Жарқурғон тумани | V33: =+D33/C33 -> 0.96629213 | W33: =+E33/C33 -> 0.033707865 | X33: =+F33/C33 -> 0
A34: 7 | B34: Қизириқ тумани | C34: =+D34+E34+F34 -> 81 | D34: =+COUNTIFS('Жами топшириқлар-1'!$H$3:$H$5027,B34,'Жами топшириқлар-1'!$I$3:$I$5027,$D$6) -> 75 | E34: =+COUNTIFS('Жами топшириқлар-1'!$H$3:$H$5027,B34,'Жами топшириқлар-1'!$I$3:$I$5027,$E$6) -> 5 | F34: =+COUNTIFS('Жами топшириқлар-1'!$H$3:$H$5027,B34,'Жами топшириқлар-1'!$I$3:$I$5027,$F$6) -> 1 | T34: =+A34 -> 7 | U34: =+B34 -> Қизириқ тумани | V34: =+D34/C34 -> 0.92592593 | W34: =+E34/C34 -> 0.061728395 | X34: =+F34/C34 -> 0.012345679
A35: 8 | B35: Қумқўрғон тумани | C35: =+D35+E35+F35 -> 80 | D35: =+COUNTIFS('Жами топшириқлар-1'!$H$3:$H$5027,B35,'Жами топшириқлар-1'!$I$3:$I$5027,$D$6) -> 75 | E35: =+COUNTIFS('Жами топшириқлар-1'!$H$3:$H$5027,B35,'Жами топшириқлар-1'!$I$3:$I$5027,$E$6) -> 5 | F35: =+COUNTIFS('Жами топшириқлар-1'!$H$3:$H$5027,B35,'Жами топшириқлар-1'!$I$3:$I$5027,$F$6) -> 0 | T35: =+A35 -> 8 | U35: =+B35 -> Қумқўрғон тумани | V35: =+D35/C35 -> 0.9375 | W35: =+E35/C35 -> 0.0625 | X35: =+F35/C35 -> 0
A36: 9 | B36: Музработ тумани | C36: =+D36+E36+F36 -> 60 | D36: =+COUNTIFS('Жами топшириқлар-1'!$H$3:$H$5027,B36,'Жами топшириқлар-1'!$I$3:$I$5027,$D$6) -> 56 | E36: =+COUNTIFS('Жами топшириқлар-1'!$H$3:$H$5027,B36,'Жами топшириқлар-1'!$I$3:$I$5027,$E$6) -> 2 | F36: =+COUNTIFS('Жами топшириқлар-1'!$H$3:$H$5027,B36,'Жами топшириқлар-1'!$I$3:$I$5027,$F$6) -> 2 | T36: =+A36 -> 9 | U36: =+B36 -> Музработ тумани | V36: =+D36/C36 -> 0.93333333 | W36: =+E36/C36 -> 0.033333333 | X36: =+F36/C36 -> 0.033333333
A37: 10 | B37: Олтинсой тумани | C37: =+D37+E37+F37 -> 49 | D37: =+COUNTIFS('Жами топшириқлар-1'!$H$3:$H$5027,B37,'Жами топшириқлар-1'!$I$3:$I$5027,$D$6) -> 46 | E37: =+COUNTIFS('Жами топшириқлар-1'!$H$3:$H$5027,B37,'Жами топшириқлар-1'!$I$3:$I$5027,$E$6) -> 2 | F37: =+COUNTIFS('Жами топшириқлар-1'!$H$3:$H$5027,B37,'Жами топшириқлар-1'!$I$3:$I$5027,$F$6) -> 1 | T37: =+A37 -> 10 | U37: =+B37 -> Олтинсой тумани | V37: =+D37/C37 -> 0.93877551 | W37: =+E37/C37 -> 0.040816327 | X37: =+F37/C37 -> 0.020408163
A38: 11 | B38: Сариосиё тумани | C38: =+D38+E38+F38 -> 69 | D38: =+COUNTIFS('Жами топшириқлар-1'!$H$3:$H$5027,B38,'Жами топшириқлар-1'!$I$3:$I$5027,$D$6) -> 67 | E38: =+COUNTIFS('Жами топшириқлар-1'!$H$3:$H$5027,B38,'Жами топшириқлар-1'!$I$3:$I$5027,$E$6) -> 2 | F38: =+COUNTIFS('Жами топшириқлар-1'!$H$3:$H$5027,B38,'Жами топшириқлар-1'!$I$3:$I$5027,$F$6) -> 0 | T38: =+A38 -> 11 | U38: =+B38 -> Сариосиё тумани | V38: =+D38/C38 -> 0.97101449 | W38: =+E38/C38 -> 0.028985507 | X38: =+F38/C38 -> 0
A39: 12 | B39: Термиз тумани | C39: =+D39+E39+F39 -> 64 | D39: =+COUNTIFS('Жами топшириқлар-1'!$H$3:$H$5027,B39,'Жами топшириқлар-1'!$I$3:$I$5027,$D$6) -> 62 | E39: =+COUNTIFS('Жами топшириқлар-1'!$H$3:$H$5027,B39,'Жами топшириқлар-1'!$I$3:$I$5027,$E$6) -> 2 | F39: =+COUNTIFS('Жами топшириқлар-1'!$H$3:$H$5027,B39,'Жами топшириқлар-1'!$I$3:$I$5027,$F$6) -> 0 | T39: =+A39 -> 12 | U39: =+B39 -> Термиз тумани | V39: =+D39/C39 -> 0.96875 | W39: =+E39/C39 -> 0.03125 | X39: =+F39/C39 -> 0
... A42: 15 | B42: Шўрчи тумани | C42: =+D42+E42+F42 -> 91 | D42: =+COUNTIFS('Жами топшириқлар-1'!$H$3:$H$5027,B42,'Жами топшириқлар-1'!$I$3:$I$5027,$D$6) -> 86 | E42: =+COUNTIFS('Жами топшириқлар-1'!$H$3:$H$5027,B42,'Жами топшириқлар-1'!$I$3:$I$5027,$E$6) -> 5 | F42: =+COUNTIFS('Жами топшириқлар-1'!$H$3:$H$5027,B42,'Жами топшириқлар-1'!$I$3:$I$5027,$F$6) -> 0 | T42: =+A42 -> 15 | U42: =+B42 -> Шўрчи тумани | V42: =+D42/C42 -> 0.94505495 | W42: =+E42/C42 -> 0.054945055 | X42: =+F42/C42 -> 0
B43: Шаҳар ва туман ҳокимликлари | C43: =+D43+E43+F43 -> 133 | D43: =+COUNTIFS('Жами топшириқлар-1'!$H$3:$H$5027,B43,'Жами топшириқлар-1'!$I$3:$I$5027,$D$6) -> 133 | E43: =+COUNTIFS('Жами топшириқлар-1'!$H$3:$H$5027,B43,'Жами топшириқлар-1'!$I$3:$I$5027,$E$6) -> 0 | F43: =+COUNTIFS('Жами топшириқлар-1'!$H$3:$H$5027,B43,'Жами топшириқлар-1'!$I$3:$I$5027,$F$6) -> 0 | T43: =+A43 -> 0 | U43: =+B43 -> Шаҳар ва туман ҳокимликлари | V43: =+D43/C43 -> 1 | W43: =+E43/C43 -> 0 | X43: =+F43/C43 -> 0

Sheet Мажмуалар
A1: Вилоят ҳокими У.Қосимов томонидан ҳудудларни ўрганиш давомида аниқланган муаммоларни бартараф этиш бўйича берилаётган тезкор топшириқларнинг ижроси тўғрисида МАЪЛУМОТ
E4: 28.10.2025 йил ҳолатига
A5: Т\Р | B5: Масъуллар | C5: Жами топшириқ сони | D5: Шундан
D6: Бажарилган | E6: Бажарилмаган | F6: Бажарилмоқда | V6: Бажарилган | W6: Бажарилмаган | X6: Бажарилмоқда
A7: ЖАМИ (Мажмуалар) | C7: =SUM(C8:C25) -> 3482 | D7: =SUM(D8:D25) -> 3370 | E7: =SUM(E8:E25) -> 68 | F7: =SUM(F8:F25) -> 44 | U7: =+A7 -> ЖАМИ (Мажмуалар) | V7: =+D7/C7 -> 0.96783458 | W7: =+E7/C7 -> 0.019529006 | X7: =+F7/C7 -> 0.012636416
A8: 1 | B8: А.Амиров | C8: =+D8+E8+F8 -> 972 | D8: =+COUNTIFS('Жами топшириқлар-1'!$H$3:$H$5027,B8,'Жами топшириқлар-1'!$I$3:$I$5027,$D$6) -> 927 | E8: =+COUNTIFS('Жами топшириқлар-1'!$H$3:$H$5027,B8,'Жами топшириқлар-1'!$I$3:$I$5027,$E$6) -> 20 | F8: =+COUNTIFS('Жами топшириқлар-1'!$H$3:$H$5027,B8,'Жами топшириқлар-1'!$I$3:$I$5027,$F$6) -> 25 | I8: Қурилиш | T8: =+A8 -> 1 | U8: =+B8 -> А.Амиров | V8: =+D8/C8 -> 0.9537037 | W8: =+E8/C8 -> 0.020576132 | X8: =+F8/C8 -> 0.025720165
A9: 2 | B9: И.Сапаров | C9: =+D9+E9+F9 -> 628 | D9: =+COUNTIFS('Жами топшириқлар-1'!$H$3:$H$5027,B9,'Жами топшириқлар-1'!$I$3:$I$5027,$D$6) -> 599 | E9: =+COUNTIFS('Жами топшириқлар-1'!$H$3:$H$5027,B9,'Жами топшириқлар-1'!$I$3:$I$5027,$E$6) -> 22 | F9: =+COUNTIFS('Жами топшириқлар-1'!$H$3:$H$5027,B9,'Жами топшириқлар-1'!$I$3:$I$5027,$F$6) -> 7 | I9: Ёшлар ва ижтимоий | T9: =+A9 -> 2 | U9: =+B9 -> И.Сапаров | V9: =+D9/C9 -> 0.95382166 | W9: =+E9/C9 -> 0.035031847 | X9: =+F9/C9 -> 0.011146497
A10: 3 | B10: Ж.Тўраев | C10: =+D10+E10+F10 -> 183 | D10: =+COUNTIFS('Жами топшириқлар-1'!$H$3:$H$5027,B10,'Жами топшириқлар-1'!$I$3:$I$5027,$D$6) -> 172 | E10: =+COUNTIFS('Жами топшириқлар-1'!$H$3:$H$5027,B10,'Жами топшириқлар-1'!$I$3:$I$5027,$E$6) -> 10 | F10: =+COUNTIFS('Жами топшириқлар-1'!$H$3:$H$5027,B10,'Жами топшириқлар-1'!$I$3:$I$5027,$F$6) -> 1 | I10: Туризм ва спорт | T10: =+A10 -> 3 | U10: =+B10 -> Ж.Тўраев | V10: =+D10/C10 -> 0.93989071 | W10: =+E10/C10 -> 0.054644809 | X10: =+F10/C10 -> 0.0054644809
A11: 4 | B11: Ш.Ражабов | C11: =+D11+E11+F11 -> 565 | D11: =+COUNTIFS('Жами топшириқлар-1'!$H$3:$H$5027,B11,'Жами топшириқлар-1'!$I$3:$I$5027,$D$6) -> 554 | E11: =+COUNTIFS('Жами топшириқлар-1'!$H$3:$H$5027,B11,'Жами топшириқлар-1'!$I$3:$I$5027,$E$6) -> 7 | F11: =+COUNTIFS('Жами топшириқлар-1'!$H$3:$H$5027,B11,'Жами топшириқлар-1'!$I$3:$I$5027,$F$6) -> 4 | I11: Иқтисод | T11: =+A11 -> 4 | U11: =+B11 -> Ш.Ражабов | V11: =+D11/C11 -> 0.98053097 | W11: =+E11/C11 -> 0.012389381 | X11: =+F11/C11 -> 0.007079646
A12: 5 | B12: Ф.Исмоилов | C12: =+D12+E12+F12 -> 386 | D12: =+COUNTIFS('Жами топшириқлар-1'!$H$3:$H$5027,B12,'Жами топшириқлар-1'!$I$3:$I$5027,$D$6) -> 382 | E12: =+COUNTIFS('Жами топшириқлар-1'!$H$3:$H$5027,B12,'Жами топшириқлар-1'!$I$3:$I$5027,$E$6) -> 2 | F12: =+COUNTIFS('Жами топшириқлар-1'!$H$3:$H$5027,B12,'Жами топшириқлар-1'!$I$3:$I$5027,$F$6) -> 2 | I12: Қишлоқ хўжалиги | T12: =+A12 -> 5 | U12: =+B12 -> Ф.Исмоилов | V12: =+D12/C12 -> 0.98963731 | W12: =+E12/C12 -> 0.0051813472 | X12: =+F12/C12 -> 0.0051813472
A13: 6 | B13: Ш.Жўраев | C13: =+D13+E13+F13 -> 209 | D13: =+COUNTIFS('Жами топшириқлар-1'!$H$3:$H$5027,B13,'Жами топшириқлар-1'!$I$3:$I$5027,$D$6) -> 205 | E13: =+COUNTIFS('Жами топшириқлар-1'!$H$3:$H$5027,B13,'Жами топшириқлар-1'!$I$3:$I$5027,$E$6) -> 4 | F13: =+COUNTIFS('Жами топшириқлар-1'!$H$3:$H$5027,B13,'Жами топшириқлар-1'!$I$3:$I$5027,$F$6) -> 0 | I13: Инвестиция | T13: =+A13 -> 6 | U13: =+B13 -> Ш.Жўраев | V13: =+D13/C13 -> 0.98086124 | W13: =+E13/C13 -> 0.019138756 | X13: =+F13/C13 -> 0
A14: 7 | B14: Э.Нарманов Солиқ (4-сектор) | C14: =+D14+E14+F14 -> 0 | D14: =+COUNTIFS('Жами топшириқлар-1'!$H$3:$H$5027,B14,'Жами топшириқлар-1'!$I$3:$I$5027,$D$6) -> 0 | E14: =+COUNTIFS('Жами топшириқлар-1'!$H$3:$H$5027,B14,'Жами топшириқлар-1'!$I$3:$I$5027,$E$6) -> 0 | F14: =+COUNTIFS('Жами топшириқлар-1'!$H$3:$H$5027,B14,'Жами топшириқлар-1'!$I$3:$I$5027,$F$6) -> 0 | I14: Вилоят, шаҳар ва туман Солиқ бошлиқлари | T14: =+A14 -> 7 | U14: =+B14 -> Э.Нарманов Солиқ (4-сектор) | V14: =+D14/C14 -> #DIV/0! | W14: =+E14/C14 -> #DIV/0! | X14: =+F14/C14 -> #DIV/0!
A15: 8 | B15: Т.Исмаилов ИИБ (3-сектор) | C15: =+D15+E15+F15 -> 0 | D15: =+COUNTIFS('Жами топшириқлар-1'!$H$3:$H$5027,B15,'Жами топшириқлар-1'!$I$3:$I$5027,$D$6) -> 0 | E15: =+COUNTIFS('Жами топшириқлар-1'!$H$3:$H$5027,B15,'Жами топшириқлар-1'!$I$3:$I$5027,$E$6) -> 0 | F15: =+COUNTIFS('Жами топшириқлар-1'!$H$3:$H$5027,B15,'Жами топшириқлар-1'!$I$3:$I$5027,$F$6) -> 0 | I15: Вилоят, шаҳар ва туман ИИБ бошлиқлари | T15: =+A15 -> 8 | U15: =+B15 -> Т.Исмаилов ИИБ (3-сектор) | V15: =+D15/C15 -> #DIV/0! | W15: =+E15/C15 -> #DIV/0! | X15: =+F15/C15 -> #DIV/0!
A16: 9 | B16: З.Назаров | C16: =+D16+E16+F16 -> 186 | D16: =+COUNTIFS('Жами топшириқлар-1'!$H$3:$H$5027,B16,'Жами топшириқлар-1'!$I$3:$I$5027,$D$6) -> 184 | E16: =+COUNTIFS('Жами топшириқлар-1'!$H$3:$H$5027,B16,'Жами топшириқлар-1'!$I$3:$I$5027,$E$6) -> 2 | F16: =+COUNTIFS('Жами топшириқлар-1'!$H$3:$H$5027,B16,'Жами топшириқлар-1'!$I$3:$I$5027,$F$6) -> 0 | I16: Харбий | T16: =+A16 -> 9 | U16: =+B16 -> З.Назаров | V16: =+D16/C16 -> 0.98924731 | W16: =+E16/C16 -> 0.010752688 | X16: =+F16/C16 -> 0
A17: 10 | B17: З.Хидирова | C17: =+D17+E17+F17 -> 55 | D17: =+COUNTIFS('Жами топшириқлар-1'!$H$3:$H$5027,B17,'Жами топшириқлар-1'!$I$3:$I$5027,$D$6) -> 54 | E17: =+COUNTIFS('Жами топшириқлар-1'!$H$3:$H$5027,B17,'Жами топшириқлар-1'!$I$3:$I$5027,$E$6) -> 1 | F17: =+COUNTIFS('Жами топшириқлар-1'!$H$3:$H$5027,B17,'Жами топшириқлар-1'!$I$3:$I$5027,$F$6) -> 0 | I17: Махалла ва оила | T17: =+A17 -> 10 | U17: =+B17 -> З.Хидирова | V17: =+D17/C17 -> 0.98181818 | W17: =+E17/C17 -> 0.018181818 | X17: =+F17/C17 -> 0
A18: 11 | B18: Б.Дониёров | C18: =+D18+E18+F18 -> 66 | D18: =+COUNTIFS('Жами топшириқлар-1'!$H$3:$H$5027,B18,'Жами топшириқлар-1'!$I$3:$I$5027,$D$6) -> 62 | E18: =+COUNTIFS('Жами топшириқлар-1'!$H$3:$H$5027,B18,'Жами топшириқлар-1'!$I$3:$I$5027,$E$6) -> 0 | F18: =+COUNTIFS('Жами топшириқлар-1'!$H$3:$H$5027,B18,'Жами топшириқлар-1'!$I$3:$I$5027,$F$6) -> 4 | I18: Мурожаатлар | T18: =+A18 -> 11 | U18: =+B18 -> Б.Дониёров | V18: =+D18/C18 -> 0.93939394 | W18: =+E18/C18 -> 0 | X18: =+F18/C18 -> 0.060606061
A19: 12 | B19: Ф.Менглиев | C19: =+D19+E19+F19 -> 171 | D19: =+COUNTIFS('Жами топшириқлар-1'!$H$3:$H$5027,B19,'Жами топшириқлар-1'!$I$3:$I$5027,$D$6) -> 171 | E19: =+COUNTIFS('Жами топшириқлар-1'!$H$3:$H$5027,B19,'Жами топшириқлар-1'!$I$3:$I$5027,$E$6) -> 0 | F19: =+COUNTIFS('Жами топшириқлар-1'!$H$3:$H$5027,B19,'Жами топшириқлар-1'!$I$3:$I$5027,$F$6) -> 0 | I19: Вил Кадр | T19: =+A19 -> 12 | U19: =+B19 -> Ф.Менглиев | V19: =+D19/C19 -> 1 | W19: =+E19/C19 -> 0 | X19: =+F19/C19 -> 0
... A21: 14 | B21: Ф.Очилдиев | C21: =+D21+E21+F21 -> 10 | D21: =+COUNTIFS('Жами топшириқлар-1'!$H$3:$H$5027,B21,'Жами топшириқлар-1'!$I$3:$I$5027,$D$6) -> 9 | E21: =+COUNTIFS('Жами топшириқлар-1'!$H$3:$H$5027,B21,'Жами топшириқлар-1'!$I$3:$I$5027,$E$6) -> 0 | F21: =+COUNTIFS('Жами топшириқлар-1'!$H$3:$H$5027,B21,'Жами топшириқлар-1'!$I$3:$I$5027,$F$6) -> 1 | I21: Ахборот тахлил | T21: =+A21 -> 14 | U21: =+B21 -> Ф.Очилдиев | V21: =+D21/C21 -> 0.9 | W21: =+E21/C21 -> 0 | X21: =+F21/C21 -> 0.1
A22: 15 | B22: О.Ашуров | C22: =+D22+E22+F22 -> 9 | D22: =+COUNTIFS('Жами топшириқлар-1'!$H$3:$H$5027,B22,'Жами топшириқлар-1'!$I$3:$I$5027,$D$6) -> 9 | E22: =+COUNTIFS('Жами топшириқлар-1'!$H$3:$H$5027,B22,'Жами топшириқлар-1'!$I$3:$I$5027,$E$6) -> 0 | F22: =+COUNTIFS('Жами топшириқлар-1'!$H$3:$H$5027,B22,'Жами топшириқлар-1'!$I$3:$I$5027,$F$6) -> 0 | T22: =+A22 -> 15 | U22: =+B22 -> О.Ашуров | V22: =+D22/C22 -> 1 | W22: =+E22/C22 -> 0 | X22: =+F22/C22 -> 0
A23: 16 | B23: М.Давлатов | C23: =+D23+E23+F23 -> 27 | D23: =+COUNTIFS('Жами топшириқлар-1'!$H$3:$H$5027,B23,'Жами топшириқлар-1'!$I$3:$I$5027,$D$6) -> 27 | E23: =+COUNTIFS('Жами топшириқлар-1'!$H$3:$H$5027,B23,'Жами топшириқлар-1'!$I$3:$I$5027,$E$6) -> 0 | F23: =+COUNTIFS('Жами топшириқлар-1'!$H$3:$H$5027,B23,'Жами топшириқлар-1'!$I$3:$I$5027,$F$6) -> 0 | T23: =+A23 -> 16 | U23: =+B23 -> М.Давлатов
A24: 17 | B24: Д.Бобоёров | C24: =+D24+E24+F24 -> 1 | D24: =+COUNTIFS('Жами топшириқлар-1'!$H$3:$H$5027,B24,'Жами топшириқлар-1'!$I$3:$I$5027,$D$6) -> 1 | E24: =+COUNTIFS('Жами топшириқлар-1'!$H$3:$H$5027,B24,'Жами топшириқлар-1'!$I$3:$I$5027,$E$6) -> 0 | F24: =+COUNTIFS('Жами топшириқлар-1'!$H$3:$H$5027,B24,'Жами топшириқлар-1'!$I$3:$I$5027,$F$6) -> 0 | T24: =+A24 -> 17 | U24: =+B24 -> Д.Бобоёров
A25: 18 | B25: С.Турдиев Прокуратура (2-сектор) | C25: =+D25+E25+F25 -> 0 | D25: =+COUNTIFS('Жами топшириқлар-1'!$H$3:$H$5027,B25,'Жами топшириқлар-1'!$I$3:$I$5027,$D$6) -> 0 | E25: =+COUNTIFS('Жами топшириқлар-1'!$H$3:$H$5027,B25,'Жами топшириқлар-1'!$I$3:$I$5027,$E$6) -> 0 | F25: =+COUNTIFS('Жами топшириқлар-1'!$H$3:$H$5027,B25,'Жами топшириқлар-1'!$I$3:$I$5027,$F$6) -> 0 | I25: Вилоят, шаҳар ва туман прокурорлари | T25: =+A25 -> 18 | U25: =+B25 -> С.Турдиев Прокуратура (2-сектор) | V25: =+D25/C25 -> #DIV/0! | W25: =+E25/C25 -> #DIV/0! | X25: =+F25/C25 -> #DIV/0!

Sheet Ташкилотлар
A1: Вилоят ҳокими У.Қосимов томонидан ҳудудларни ўрганиш давомида аниқланган муаммоларни бартараф этиш бўйича берилаётган тезкор топшириқларнинг ижроси тўғрисида МАЪЛУМОТ (БАЖАРИЛМАГАН)
C4: 16.08.2025 йил
A5: Т/р | B5: Ташкилот ва идора номи | C5: Бажарилмаган топшириқлар
A6: 1 | B6: “Сурхондарёавтойўл” Ҳудудий йўллардан фойдаланиш ташкилоти директори Хотамов Баходир | C6: 4
A7: =+A6+1 -> 2 | B7: Сурхондарё вилояти Мактабгача ва мактаб таьлими бошқармаси бошлиғи Мамадиев Хусниддин Норбоевич | C7: 3
A8: =+A7+1 -> 3 | B8: Сурхондарё минтақавий йўлларга буюртмачи хизмати давлат унитар корхонаси директори (Умаров Турдимурод Абдураимович) | C8: 3
A9: =+A8+1 -> 4 | B9: Сурхондарё вилоят ҳокимлиги ҳузуридаги “Кичик саноат зоналарини бошқариш ягона дирекцияси” давлат муассасаси директори (Ортиков Бахтияр Бегимкулович) | C9: 3
A10: =+A9+1 -> 5 | B10: Кадастр агентлиги Сурхондарё вилояти бошқармаси бошлиғи Абдирахманов Менглимамат Абдишукурович | C10: 2
A11: =+A10+1 -> 6 | B11: Кадастр агентлиги ҳузуридаги Давлат кадастрлари палатасининг Сурхондарё вилояти бошқармаси бошлиғи в.б Шаймарданов Собир Хушбоқович | C11: 2
A12: =+A11+1 -> 7 | B12: Сурхондарё вилояти соғлиқни сақлаш бошқармаси бошлиғи Абдивохидов Комил Муртазаевич | C12: 2
A13: =+A12+1 -> 8 | B13: Вилоят Марказий банк бош бошқармаси бошлиғи Ражабов Азамат | C13: 2
A14: =+A13+1 -> 9 | B14: “Ҳудудий электр тармоқлари” АЖ Сурхондарё ҳудудий филиали директори Шамсиддинов Маъруфжон Курбонович | C14: 1
A15: =+A14+1 -> 10 | B15: Вилояти Камбағалликни қисқартириш ва бандлик бошқармаси бошлиғи Яқубов Одилжон Алмахамадович | C15: 1
A16: =+A15+1 -> 11 | B16: Сурхондарё вилояти маданият бошқармаси бошлиғи Норбоев Умид | C16: 1
A17: =+A16+1 -> 12 | B17: Бизнесни ривожлантириш банки АТБ Сурхондарё вилояти ҳудудий бошқармаси бошқарувчиси Т.Жўраев | C17: 1
A18: =+A17+1 -> 13 | B18: Сув таъминоти ва оқова сув объектлари қурилиши бўйича инжинеринг компанияси УК вилоят ҳудудий бошқармаси Ж.Аннаматов | C18: 1
... A21: =+A20+1 -> 16 | B21: Вилоят маҳаллалари уюшмаси бошқармаси бошлиғи С.Абдураимов | C21: 1
A22: =+A21+1 -> 17 | B22: Сурхондарё вилояти қурилиш ва уй-жой коммунал хўжалиги бошқармаси (Тангриев Панжи Қобилович)
A23: =+A22+1 -> 18 | B23: Транспорт назорат инспекцияси Х.Абдизоиров
A24: =+A23+1 -> 19 | B24: Туризм бошқармаси бошлиғи ўринбосари Д.Хафизов
A25: =+A24+1 -> 20 | B25: Сурхондарё вилояти қишлоқ хўжалиги бошқармаси бошлиғи ўринбосари Гаппаров Рахматулло Бобохонович
A26: =+A25+1 -> 21 | B26: Миллий банк Мамараджабов Бобур Эргашевич
A27: =+A26+1 -> 22 | B27: Давлат активларини бошқариш агентлигининг Сурхондарё вилояти ҳудудий бошқармаси бошлиғи (Худойбердиев Самандар Каландарович)
A28: =+A27+1 -> 23 | B28: Сурхондарё вилояти спортни ривожлантириш бош бошқармаси бошлиғи в.в.б. Шомуродов Санжар Азамат ўғли
A29: =+A28+1 -> 24 | B29: Насос станциялари, энергетика бошқармаси Т.Кучкинов (УНС)
A30: =+A29+1 -> 25 | B30: Вилоят ветеринария ва чорвачиликни ривожлантириш бошқармаси А.Юсупов
A31: =+A30+1 -> 26 | B31: “Ўзсаноатқурилишбанк” АТБ Сурхондарё минтақавий филиал бошлиғи С.Абдурахмонов
A32: =+A31+1 -> 27 | B32: Сурхондарё вилояти ҳокимлиги ҳузуридаги “Ягона буюртмачи хизмати” ДУК директори Йулдошев Ахмад Асодович
A33: =+A32+1 -> 28 | B33: Инфратузилмани ривожлантириш инженеринг компанияси давлат муассаси Сурхондарё вилояти ҳудудий бўлинмаси бошлиғи Зоиров Махмуд Абдураимович
... A73: =+A72+1 -> 68 | B73: Халқ қабулхонаси
A74: ЖАМИ | C74: =SUM(C6:C72) -> 29

Sheet Туманлар
A1: Вилоят ҳокими У.Қосимов томонидан ҳудудларни ўрганиш давомида аниқланган муаммоларни бартараф этиш бўйича берилаётган тезкор топшириқларнинг ижроси тўғрисида МАЪЛУМОТ (БАЖАРИЛМАГАН)
E4: 28.10.2025 йил
A5: Т\Р | B5: Масъуллар | C5: Бажарилмаган топшириқ сони | D5: Шундан | F5: Изох
D6: Туман ижрочи | E6: Вилоят, Шаҳар ва туман ҳокимликлари биргаликда
A7: 1 | B7: Термиз шаҳар | C7: =+D7+E7 -> 21 | D7: 21 | N7: 1 | O7: Термиз шаҳар
A8: =+A7+1 -> 2 | B8: Ангор тумани | C8: =+D8+E8 -> 0 | N8: 2 | O8: Ангор тумани
A9: =+A8+1 -> 3 | B9: Бандихон тумани | C9: =+D9+E9 -> 0 | N9: 3 | O9: Бандихон тумани
A10: =+A9+1 -> 4 | B10: Бойсун тумани | C10: =+D10+E10 -> 0 | N10: 4 | O10: Бойсун тумани
A11: =+A10+1 -> 5 | B11: Денов тумани | C11: =+D11+E11 -> 0 | N11: 5 | O11: Денов тумани
A12: =+A11+1 -> 6 | B12: Жарқурғон тумани | C12: =+D12+E12 -> 0 | N12: 6 | O12: Жарқурғон тумани
A13: =+A12+1 -> 7 | B13: Қизириқ тумани | C13: =+D13+E13 -> 0 | N13: 7 | O13: Қизириқ тумани
A14: =+A13+1 -> 8 | B14: Қумқўрғон тумани | C14: =+D14+E14 -> 0 | N14: 8 | O14: Қумқўрғон тумани
A15: =+A14+1 -> 9 | B15: Музработ тумани | C15: =+D15+E15 -> 0 | N15: 9 | O15: Музработ тумани
A16: =+A15+1 -> 10 | B16: Олтинсой тумани | C16: =+D16+E16 -> 0 | N16: 10 | O16: Олтинсой тумани
A17: =+A16+1 -> 11 | B17: Сариосиё тумани | C17: =+D17+E17 -> 0 | N17: 11 | O17: Сариосиё тумани
A18: =+A17+1 -> 12 | B18: Термиз тумани | C18: =+D18+E18 -> 0 | N18: 12 | O18: Термиз тумани
A19: =+A18+1 -> 13 | B19: Узун тумани | C19: =+D19+E19 -> 0 | N19: 13 | O19: Узун тумани
... A21: =+A20+1 -> 15 | B21: Шўрчи тумани | C21: =+D21+E21 -> 0 | N21: 15 | O21: Шўрчи тумани
A22: ЖАМИ | C22: =SUM(C7:C21) -> 21 | D22: =SUM(D7:D21) -> 21 | E22: =SUM(E7:E21) -> 0 | L22: =SUM(L7:L21) -> 0 | N22: ЖАМИ | P22: =SUM(P7:P21) -> 0

Sheet ташкилот тушунтириш хати
A1: Вилоят ҳокими У.Қосимов томонидан ҳудудларни ўрганиш давомида аниқланган муаммоларни бартараф этиш бўйича берилаётган тезкор топшириқларнинг ижроси тўғрисида МАЪЛУМОТ (БАЖАРИЛМАГАН)
F4: 21.10.2024 йил
A5: Т/р | B5: Топшириқларнинг ижросига масъул бўлган ташкилот ва идоралар | C5: Бажарилмаган топшириқлар | D5: Тушунтириш хатлари тақдим этилиши | E5: Мажмуа номи
A6: 1 | B6: “Сурхондарёавтойўл” Ҳудудий йўллардан фойдаланиш ташкилоти директори Хотамов Баходир Чоршамиевич | C6: 7 | D6: тақдим этилди | E6: А.Амиров | F6: Қурилиш мажмуаси
A7: =+A6+1 -> 2 | B7: Сурхондарё вилояти Мактабгача ва мактаб таьлими бошқармаси бошлиғи Мамадиев Хусниддин Норбоевич | C7: 7 | D7: тақдим этилмади | E7: И.Сапаров | F7: Ёшлар мажмуаси
A8: =+A7+1 -> 3 | B8: “Ҳудудий электр тармоқлари” АЖ Сурхондарё ҳудудий филиали директори Шамсиддинов Маъруфжон Курбонович | C8: 3 | D8: тақдим этилди | E8: А.Амиров | F8: Қурилиш мажмуаси
A9: =+A8+1 -> 4 | B9: Вилоят ва туман (шаҳар) прокуратураси
A10: 4 | B10: Сурхондарё вилояти ҳокимлиги ҳузуридаги “Ягона буюртмачи хизмати” ДУК директори Йулдошев Ахмад Асодович | C10: 2 | D10: тақдим этилди | E10: А.Амиров | F10: Қурилиш мажмуаси
A11: =+A10+1 -> 5 | B11: Сурхондарё вилояти солиқ бошқармаси (Нарманов Эркин Абдуалимович) | C11: 2 | D11: тақдим этилди | E11: Иқтисодиёт мажмуаси | F11: Иқтисодиёт мажмуаси
A12: =+A11+1 -> 6 | B12: Кадастр агентлиги ҳузуридаги Давлат кадастрлари палатасининг Сурхондарё вилояти бошқармаси бошлиғи (Сувонов Шаҳобиддин Мусурмон ўғли) | C12: 1 | D12: тақдим этилди | E12: Иқтисодиёт мажмуаси | F12: Иқтисодиёт мажмуаси
A13: =+A12+1 -> 7 | B13: Кадастр агентлиги Сурхондарё вилояти бошқармаси бошлиғи (Абдирахманов Менглимамат Абдишукурович) | C13: 1 | D13: тақдим этилди | E13: Ш.Ражабов | F13: Иқтисодиёт мажмуаси
A14: =+A13+1 -> 8 | B14: “Агробанк” акциядорик тижорат банкининг Сурхондарё вилояти бошқармаси бошлиғи Раджабов Шухрат Бахтиёрович | C14: 1 | D14: тақдим этилди | E14: Ш.Ражабов | F14: Иқтисодиёт мажмуаси
A15: =+A14+1 -> 9 | B15: Сурхондарё вилояти “Агропилла” масъулияти чекланган жамияти раиси Абдуллаев Акмал Абдусалимович | C15: 1 | D15: тақдим этилмади | E15: Ф.Исмоилов | F15: Қишлоқ хўжалиги мажмуаси
A16: =+A15+1 -> 10 | B16: Туронбанк акциядорлик-тижорат банки Сурхондарё банк хизматлар маркази рахбари Маматалиев Искандар Рашидович | C16: 1 | D16: тақдим этилди | E16: Ш.Ражабов | F16: Иқтисодиёт мажмуаси
A17: =+A16+1 -> 11 | B17: Вилоят ва туман (шаҳар) ИИБ (Исмаилов Тимур Камалатдинович)
A18: 11 | B18: Ичимлик сув ва оқова сув қурилиши бўйича ИК Б.Имомов | C18: 1 | D18: тақдим этилди | E18: А.Амиров | F18: Қурилиш мажмуаси
A19: =+A18+1 -> 12 | B19: Сурхондарё вилояти қурилиш соҳасидаги худудий назорат инспекцияси бошлиғи Лолаев Шарофиддин Усанович (ГАСН) | C19: 1 | D19: тақдим этилди | E19: А.Амиров | F19: Қурилиш мажмуаси
A20: =+A19+1 -> 13 | B20: Сурхондарё вилояти қурилиш ва уй-жой коммунал хўжалиги бошқармаси (Тангиров Панжи Қобилович)
A21: =+A20+1 -> 14 | B21: Вилоят маҳаллалари уюшмаси бошқармаси бошлиғи С.Абдураимов
A22: =+A21+1 -> 15 | B22: “Аму-Сурхон” ирригация тизимлари хавза бошкармаси бошлиғи Б.Алимов,
A23: =+A22+1 -> 16 | B23: Бизнесни ривожлантириш банки АТБ Сурхондарё вилояти ҳудудий бошқармаси бошқарувчиси (Утаганов Мамур Иргашович)
A24: =+A23+1 -> 17 | B24: Сурхондарё вилояти қишлоқ хўжалиги бошқармаси бошлиғи Гаппаров Рахматулло Бобохонович
A25: =+A24+1 -> 18 | B25: Сурхондарё вилояти соғлиқни сақлаш бошқармаси бошлиғи (Абдивохидов Комил Муртазаевич)
A26: =+A25+1 -> 19 | B26: Сурхондарё минтақавий йўлларга буюртмачи хизмати давлат унитар корхонаси директори (Умаров Турдимурод Абдураимович)
A27: =+A26+1 -> 20 | B27: Сурхондарё вилояти Иқтисодиёт ва молия бош бошқармаси бошлиғи Нормуминов Жуманазар Равшанович
A28: =+A27+1 -> 21 | B28: “Ҳудудгаз Сурхондарё” газ таъминоти филиали директори Мансуров Мирзоқул Абдухофизович
A29: =+A28+1 -> 22 | B29: Сурхондарё вилояти Фавқулотда вазиятлар бошқармаси бошлиғи в.в.б. Дарханов Муроджон Қурбонназарович
A30: =+A29+1 -> 23 | B30: Сурхондарё вилоят ҳокимлиги ҳузуридаги “Кичик саноат зоналарини бошқариш ягона дирекцияси” давлат муассасаси директори (Ортиков Бахтияр Бегимкулович)
A31: =+A30+1 -> 24 | B31: Ўзбекистон Республикаси Бош прокуратураси ҳузуридаги Мажбурий ижро бюросининг Сурхондарё вилояти бошқармаси бошлиғи (Халмуратов Азамат Пайзилович)
... A45: =+A44+1 -> 38 | B45: Халқ қабулхонаси
A46: ЖАМИ | C46: =SUM(C6:C44) -> 28
B47: Тушунтириш хатлари

Sheet туман тушунтириш хати
A1: Вилоят ҳокими У.Қосимов томонидан ҳудудларни ўрганиш давомида аниқланган муаммоларни бартараф этиш бўйича берилаётган тезкор топшириқларнинг ижроси тўғрисида МАЪЛУМОТ (БАЖАРИЛМАГАН)
E4: 04.10.2024 йил
A5: Т\Р | B5: Масъуллар | C5: Бажарилмаган топшириқ сони | D5: Тушунтириш хатлари тақдим этилиши | E5: Изох
A7: 1 | B7: Ангор тумани | C7: 4 | D7: тақдим этилди | M7: 1 | N7: Термиз шаҳар
A8: =+A7+1 -> 2 | B8: Бандихон тумани | C8: 6 | D8: тақдим этилди | M8: 2 | N8: Ангор тумани
A9: =+A8+1 -> 3 | B9: Бойсун тумани | C9: 5 | D9: тақдим этилди | M9: 3 | N9: Бандихон тумани
A10: =+A9+1 -> 4 | B10: Денов тумани | C10: 4 | D10: тақдим этилди | M10: 4 | N10: Бойсун тумани
A11: =+A10+1 -> 5 | B11: Жарқурғон тумани | C11: 5 | D11: тақдим этилди | M11: 5 | N11: Денов тумани
A12: =+A11+1 -> 6 | B12: Қизириқ тумани | C12: 2 | D12: тақдим этилмади | M12: 6 | N12: Жарқурғон тумани
A13: =+A12+1 -> 7 | B13: Қумқўрғон тумани | C13: 3 | D13: тақдим этилди | M13: 7 | N13: Қизириқ тумани
A14: =+A13+1 -> 8 | B14: Музработ тумани | C14: 9 | D14: тақдим этилмади | M14: 8 | N14: Қумқўрғон тумани
A15: =+A14+1 -> 9 | B15: Олтинсой тумани | C15: 4 | D15: тақдим этилди | M15: 9 | N15: Музработ тумани
A16: =+A15+1 -> 10 | B16: Сариосиё тумани | C16: 6 | D16: тақдим этилмади | M16: 10 | N16: Олтинсой тумани
A17: =+A16+1 -> 11 | B17: Термиз тумани | C17: 4 | D17: тақдим этилди | M17: 11 | N17: Сариосиё тумани
A18: =+A17+1 -> 12 | B18: Термиз шаҳар | C18: 5 | D18: тақдим этилмади | M18: 12 | N18: Термиз тумани
A19: =+A18+1 -> 13 | B19: Узун тумани | C19: 4 | D19: тақдим этилмади | M19: 13 | N19: Узун тумани
... A21: =+A20+1 -> 15 | B21: Шўрчи тумани | C21: 3 | D21: тақдим этилди | M21: 15 | N21: Шўрчи тумани
A22: ЖАМИ | C22: =SUM(C7:C21) -> 68 | D22: =SUM(D7:D21) -> 0 | K22: =SUM(K7:K21) -> 0 | M22: ЖАМИ | O22: =SUM(O7:O21) -> 0

Sheet Каттага бажарилган
A1: Вилоят ҳокими У.Қосимов томонидан ҳудудларни ўрганиш давомида аниқланган муаммоларни бартараф этиш бўйича берилаётган тезкор топшириқларнинг ижроси тўғрисида МАЪЛУМОТ (24.05.2023) Бажарилган
A3: Т/Р | B3: Банд | C3: Топшириқ берилган сана | D3: Топшириқ берилган жой | E3: Топшириқ мазмуни | F3: Ижро муддати | G3: Асосий ижрочи маъсуллар | H3: Вилоят ҳокимлиги, шаҳар ва туман ҳокимликлари масъуллар
A4: 1 | B4: 649 | C4: 17.01.2023 | D4: Шўрчи тумани | E4: Шўрчи тумани "Мустақиллик" МФЙдаги саломатлик йўлакларини қайта қуриш ёки бурчатка териш. | F4: 45066 | G4: Шўрчи тумани ҳокими | H4: Шўрчи тумани
A5: 2 | B5: 735 | C5: 21.01.2023 | D5: Штаб йиғилиш | E5: 1 апрелга қадар санъаткорларни тўлиқ лицензия олган ҳолда ишлаши масаласини якунлаш. | F5: 45020 | G5: “Ўзбекконцерт” давлат муассасаси Сурхондарё вилояти бўлими (И.Темиров). | H5: Ж.Тўраев
A6: 3 | B6: 761 | C6: 21.01.2023 | D6: Ангор тумани | E6: Бандихон, Шўрчи, Қумқўрғон туманлари ва Термиз шаҳрида арзон уй-жойлар қуриш ишларини бошлаш. | F6: 45066 | G6: Вилоят Халқ қабулхонаси (А.Эшмуродов), Қурилиш бошқармаси (К.Эшматов). Бандихон, Шўрчи, Қумқўрғон туманлари ва Термиз шаҳар хокимликлари | H6: А.Хидиров
A7: 4 | B7: 879 | C7: 29.01.2023 | D7: Узун тумани | E7: Узун туманидаги мавжуд 46 та кўп қаватли уй-жойларда таъмирлаш ва ободонлаштириш ишларини якунлаш. | F7: 45036 | G7: Узун тумани ҳокими ва сектор раҳбарлари. | H7: Узун тумани
A8: 5 | B8: 1023 | C8: 05.02.2023 | D8: Денов туманида семинар | E8: Туман ва шаҳарларда 1 тадан маҳаллаларни муқобил энергияга ўтказиш бўйича намунавий қилиш. | F8: 20.03.2023 | G8: Ангор, Жарқўрғон, Қизириқ, Музработ, Олтинсой, Узун, Термиз туман, туман ҳокимлари | H8: Шаҳар ва туман ҳокимликлари
A9: 6 | B9: 1212 | C9: 44995 | D9: Зоом йиғилиш | E9: Қумқўрғон туманидаги 4 та сектор котибларига хайфсан берилсин ва ойлик иш хақини 30 % миқдорида жарима жазоси қўлланилсин. | F9: 44996 | G9: Қумқўрғон тумани ҳокими ва сектор раҳбарлари. | H9: Қумқўрғон тумани
A10: 7 | B10: 1233 | C10: 45000 | D10: Шеробод тумани | E10: Шеробод тумани "Мехробод" махалласидаги уйи ёнган фуқаро Жумаев Мансурга (90-721-21-80) 20 т цемент, 30 минг дона ғишт ва страпллар етказиб бериш. | F10: 45066 | G10: Вилоят хокимининг ўринбосари А.Хидиров, Туман ИИБ | H10: А.Хидиров
A11: 8 | B11: 1351 | C11: 01.04.2023 | D11: Қишлоқ хўжалиги бўйича селектр | E11: Денов туманида фермер хўжаликларининг (йиғилишга кечикиб киран 2 та фермернинг) ер майдонини давлат захирасига қайтариш. | F11: 45061 | G11: Денов тумани ҳокими, Денов тумани прокурори. | H11: Денов тумани
A12: 9 | B12: 1415 | C12: 45031 | D12: Жарқўрғон тумани | E12: Ўзбекистон Республикаси Президентининг ПҚ-57-сонли қарорнинг 2-иловасига мувофиқ ижтимоий соҳа обйектлари ва давлат идораларида кичик қувватдаги панеллар ўрнатиш ишларни ташкиллаштирмаганлиги сабабли Бойсун ва Узун туманлари ҳокимларининг биринчи ўринбосарларига ҳайфсан интизомий жазоси берилсин ҳамда Олтинсой ва Бандихон туманлари ҳокимларининг биринчи ўринбосарлари огоҳлантирилсин | F12: 45040 | G12: Олтинсой туман хокимлари | H12: Шаҳар ва туман ҳокимликлари
A13: 10 | B13: 1420 | C13: 45031 | D13: Жарқўрғон тумани | E13: Ўзбекистон Республикаси Президентининг ПҚ-57-сонли қарорнинг 7-иловасига мувофиқ ижтимоий соҳа обйектларининг локал иситиш тизимларини кўмир ёқилғисига ўтказиш бўйича топшириқлар ижроси ўз ҳолига ташлаб қўйилганлиги сабабли вилоят Иқтисодиёт ва молия бош бошқармаси бошлиғи вазифасини вақтинча бажарувчиси Ж.Нормўминов, Олтинсой тумани Иқтисодиёт ва молия бўлими бошлиғи Ж.Жўрайев ҳамда Денов тумани Иқтисодиёт ва молия бўлими бошлиғи А.Мухаммадиевларга ҳайфсан интизомий жазоси берилсин. | F13: 45040 | G13: Олтинсой тумани хокимлиги | H13: Олтинсой тумани
A14: 11 | B14: 1429 | C14: 45020 | D14: Шеробод тумани | E14: Шеробод туманида бозор рўпарасидаги автошохбекат ҳамда ер ости тунел йўлини реконструкция қилиш. Машиналарни жойлашувини автошохбекатга кўчириш. | F14: 45066 | G14: Шеробод туман хокими, туман прокурори, туман ИИБ бошлиғи, | H14: Шеробод тумани
A15: 12 | B15: 1440 | C15: 45038 | D15: Шеробод тумани | E15: Шеробод тумани бозор қаршисидаги ва атрофидаги кўп қаватли уй-жойларга сув чиқариш. (Бозорова Фотима 99-150-64-65) | F15: 45056 | G15: Шеробод туман хокими З.Халилов ва туман сектор раҳбарлари | H15: Шеробод тумани
A16: 13 | B16: 1453 | C16: 45042 | D16: Қишлоқ хўжалиги бўйича ўтказилган йиғилиш | E16: Вилоя солиқ 144 та фермер хўжалигини хисоб рақамларини очиш | F16: 45050 | G16: Вилоят ДСИ бошлиғи Э.Нарманов | H16: Ф.Исмоилов
A17: 14 | B17: 1467 | C17: 45042 | D17: Ангор туманида | E17: Тижорат банклари автобуслар харид қилиш бўйича лойиҳа ташаббускорлари рўйхатини олиб кириш | F17: 45061 | G17: Марказий банк (А.Тўхтаев), барча тижорат банк раҳбарлари | H17: А.Орипов
A18: 15 | B18: 1469 | C18: 45042 | D18: Ангор туманида | E18: Вилоят Молия бош бошқармаси вилоят ЙҲХБ бошлиғи билан ишлаб камера ва ситуацион марказ ташкил этиш учун авансларни ташлаб бериш | F18: 45066 | G18: Молия бош бошқармаси (Ж.Нормуминов), Вилоят ИИБ ЙҲХБ. | H18: А.Орипов
A19: 16 | B19: 1477 | C19: 45042 | D19: Қизириқ туманида ўтказилган видеоселектор йиғилишида | E19: Бир ҳафта муддатда Ёшлар масалалари бўйича яратилган янги тизим юзасидан берилган топшириқлар ижроси бўйича энг охирги ўринда қолган 20 та ёшлар етакчиларининг эгаллаб турган лавозимида қолиш-қолмаслик масаласи кўриб чиқилсин. | F19: 45050 | G19: Ёшлар ишлари агентлиги вилоят бошқармаси Ж.Чориев | H19: И.Сапаров
A20: 17 | B20: 1487 | C20: 45043 | D20: Қумқўрғон тумани | E20: Қумқўрғон тумани "Шерози" маҳалласидаги оқава сув (ариқ) қувурларини таъмирлаш. | F20: 45054 | G20: “Аму-Сурхон” ирригация тизимлари хавза бошкармаси бошлиғи (Т.Алимов), Қумқўрғон туман ҳокими ва сектор рахбари | H20: Қумқўрғон тумани
A21: 18 | B21: 1488 | C21: 45043 | D21: Қумқўрғон тумани | E21: Қумқўрғон тумани "Азларсой" маҳалласидаги насосни таъмирлаш | F21: 45066 | G21: Насос станциялари, энергетика бошқармаси (А.Абдураимов), Қумқўрғон туман ҳокими ва сектор рахбари | H21: Қумқўрғон тумани
A22: 19 | B22: 1501 | C22: 45043 | E22: Термиз шаҳар (13-17-мактаблар), Бойсун (5-мактаб), Жарқўрғон (2-11-21-23 мактаблар) Денов (22-80-81-мактаблар), Олтинсой (3-26-мактаб), Қумқўрғон (10-мактаб), Узун (16-мактаб), Шеробод (35-мактаб) Сариосиё (5-мактаб)да сектор раҳбарлари жиноятчиликни олдини олиш бўйича давра сухбатлари ва семинарлар ўтказсин. | F22: 45058 | G22: Термиз шаҳар, Жарқўрғон, туманлари хокимлари ва сектор раҳбарлари | H22: Шаҳар ва туман ҳокимликлари
A23: 20 | B23: 1542 | C23: 45059 | D23: Шеробод тумани | E23: Вилоят хокими жорий йилнинг 20 май куни Шеробод туманига ташрифи чоғида кийим кечак ва озиқ овқат бозирида савдо қилаёт савдогарларни таклифларини тўлиқ ўрганиб чиқиш, ҳамда озиқ овқат бозорини йўлини асфалт ишларини якунлаш. Таклифлар бўйича охирги қарорни вилоят хокимини шахсан ўзлари беради. | F23: 45066 | G23: Шеробод тумани хокими З.Халилов ва туман сектор раҳбарлари. Шеробод туман хокимининг биринчи ўринбосари У.Панжиев | H23: Шеробод тумани
A24: 21 | B24: 1543 | C24: 45059 | E24: Термиз халқаро Аерапортидан ангор туманигача бориш йўлидаги ҳамда КАРГОга бориш йўлидаги йўллар атрофини ободонлаштириш ишларини якунлаш, чиқиндиларни олиб чиқиш, кўкаламзорлаштириш ишларини якунлаш. | F24: 45065 | G24: Термиз шаҳар, Ангор тумани, Термиз тумани хокимликлари | H24: Шаҳар ва туман ҳокимликлари
A25: 22 | B25: 1565 | C25: 45063 | D25: Термиз шаҳар | E25: М.Муродов 3 кун ичида газон ўрадиган техникаларни инвентаризациядан ўтказсин. | F25: 45066 | G25: "Яшил ҳудуд" ДУК (М.Муродов) Термиз шаҳар ҳокими Ў.Тўраев | H25: Термиз шаҳар

Sheet Каттага Бажарилмоқда
A1: Вилоят ҳокими У.Қосимов томонидан ҳудудларни ўрганиш давомида аниқланган муаммоларни бартараф этиш бўйича берилаётган тезкор топшириқларнинг ижроси тўғрисида МАЪЛУМОТ (01.04.2024) Бажарилмоқда
A3: Т/Р | B3: Т/Р | C3: Банд | D3: Топшириқ берилган сана | E3: Топшириқ берилган жой | F3: Топшириқ мазмуни | G3: Ижро муддати | H3: Назорат ҳолати | I3: Асосий ижрочи маъсуллар | J3: Вилоят ҳокимлиги, шаҳар ва туман ҳокимликлари масъуллар | K3: Ижро ҳолати | L3: Изох
B4: 1 | C4: 1892 | D4: 45304 | E4: Йиғилишда | F4: Қумқурғон тумани ИТ марказини таъмирлаш. | G4: 45392 | I4: Қумқўрғон тумани хокими А.Нормаматов | J4: И.Сапаров | K4: Бажарилмоқда | L4: Таъмирлаш ишлари бошланган. Жихозлаш ишлари қолган. (15.03.2024) Муддати 10 кунга узайтирилди.
B5: 2 | C5: 1893 | D5: 45304 | F5: Ижтимоий ҳимоя платформасига киритилган кам таъминланганлар рўйхатини шаклантириб бориш. | G5: 45397 | I5: Ижтимоий ҳимой миллий агенлиги.М.Тоғаев | L5: 2024 йил 1 октябргача 144 494 та оила (20,08 %) га камайтириш чоралари белгилаб олиниб зарурий чора тадбирлар ишлаб чикилди. Феврал ойида нафака олувчи оилалар камрови 209 585 та оила (30,1 %) прогноз килиниб, режага нисбатан 30 977 тага ортиги билан кискартирилиб, амалда 178 608 та оила (25,7%)га кискартирилди хамда бюджетга 28,0 млрд.сум маблаглар иктисод килинди.
B6: 3 | C6: 1919 | D6: 45319 | E6: Йиғилишда | F6: Кейинги йил Денов туманида 2050 тарихини қилиш бўйича таёргарлик кўриш. | G6: 45658 | I6: Денов туман ҳокими (И.Аброров) | J6: А.Орипов | K6: Бажарилмоқда
B7: 4 | C7: 1931 | D7: 45336 | E7: Йиғилишда | F7: Термиз шаҳар "Тинчлик" маҳалласи Ёшлар етакчисини вазифасига совуққонлик билан қараганлиги учун амалдаги қонун ҳужжатлари асосида эгалаб турган лавозимидан озод қилиш. | G7: 45379 | I7: Вилоят ҳокимлиги Ташкилий-кадрлар гуруҳи раҳбари Ф.Менглиев, Термиз шаҳар хокими Ў.Тўраев | J7: И.Сапаров | K7: Бажарилмоқда | L7: Ёшлар етакчисини аризаси олинган. Рахбариятга қўшимча ахборот берилади.
B8: 6 | C8: 1935 | D8: 45336 | F8: Термиз шаҳар "Мангузар" маҳалласидаги фуқаро Исоқова Гулшод опани (99-029-11-60) уйини ошхонаси қуриш ва таъмирлаш | G8: 45389 | I8: Термиз шаҳар хокими Ў.Тўраев | L8: 5 халта цемент билан 200 дона ғишт олиб берилган. Фундамент ишлари қилинган.Фундамент қуригандан ишлар давом этади. Фуқаро билан гаплашилди. (15.03.2024) Топшириқ тўлиқ бажарилгач фуқародан ташаккурнома, расм ва видеолари тақдим этилсин.
B9: 7 | C9: 1952 | D9: 45346 | F9: Сариосиё, Денов ва Музработ туманларидаги канализация ишларини бошлаш. | G9: 45398 | I9: Ичимлик сув ва оқова сув қурилиши бўйича инжинеринг компанияси ҳудудий бошқармаси (Ю.Менглиев) | L9: Сариосиё ва Музработ туманларида ишлар бошланган. Денов туманида "Сурхон Диёр" мфйдаги объектда пудратчи "Сайин сув иншоотлари" МЧЖ рахбари ва бошқарув ходимлари йўқлиги сабабли молиялаштириш очишнинг имкони бўлмаяпти ва объектда ишлар тўхтаб турибти. муддат берилган 2 хафта
B10: 8 | C10: 1953 | D10: 45346 | F10: А.Сувонқулов душанба куни харбий прокуратурани пулини чиқариши керак. | G10: 45376 | I10: Вилоят хокимлиги «Ягона буюртмачи хизмати» ИК (А.Сувонқулов) | L10: Термиз ҳарбий прокуратурасига бериш учун танланган вилоят Солик бошқармаси балансидаги бинони Термиз ҳарбий прокуратураси тасарруфига беғараз ўтказиб берилишида амалий ёрдам сўраб вилоят ҳокимлиги томонидан ВМга хамда 3 4 та вазирлик идораларга 21 феврал ва 02 март кунлари алоқа хатлари юборилган. 25 мартга қадар узайтирилишини сўраб хат билан чиқишган.
B11: 9 | C11: 1957 | D11: 45346 | E11: Шўрчи тумани | F11: КПИни мактабларда жорий қилиш. Хар шанба ва душанба кунлари ахборот бериш | I11: Вилоят хокимининг ўринбосари И.Сапаров, Вилоят Мактабгача ва мактаб таълими бошқармаси бошлиғи (Х.Мамадиев). | J11: А.Орипов | K11: Бажарилмоқда | L11: Лойиҳа ишлаб чиқилмоқда
B12: 10 | C12: 1962 | D12: 45346 | E12: Шўрчи тумани | F12: Қумқўрғон Қарсоқлидаги боғчани шанба кунига қадар якунлаш. | G12: 45397 | I12: Вилоят хокимлиги «Ягона буюртмачи хизмати» ИК (А.Сувонқулов) | J12: Шўрчи тумани | K12: Бажарилмоқда | L12: Ишлар давом этмоқда. Тугалланиш арафасида.
B13: 11 | C13: 1970 | D13: 45348 | E13: Термиз шаҳар | F13: Шўрчи туманидаги тадбиркор Боймуродов томонидан қурилган кўп қаватли уйларни сотиш. | G13: 45397 | I13: Вилоят хокимининг биринчи ўринбосари А.Орипов. Вилоят Ипотека банк, Шўрчи тумани хокими У.Зокиров. | J13: Термиз шаҳар | K13: Бажарилмоқда | L13: Ҳозирги кунда ушбу топшириқ бўйича ишлар бошланган.Ижтимоий тармоқларда эълонлар берилмоқда
B14: 12 | C14: 1972 | D14: 45348 | F14: Шўрчи туманидаги фуқаро Қурбонов Нурмухаммадга (90-072-66-73) субсидия, кредит ёки моддий ёрдам бўйича амалий ёрдам бериш. Туман 3-секторга топшириқ берилган. (Топшириқ бажарилгач фуқародан ташаккурнома, расм ва видеолавҳалар илова қилинсин). | G14: 45363 | I14: Шўрчи тумани ИИБ бошлиғи, Шўрчи туман хокимлиги У.Зокиров | L14: Фуқаро субсидия, кредит ёки моддий ёрдам сўрамоқда. Фуқаро Н.Қурбоновга 2023 йилда деҳқончилик қилиши учун 15 млн кредит олиб берилган ва ҳозирги кунда ушбу кредитдан қарздорлиги мавжуд. Турмуш ўртоғи Д.Сайдуллаева 2023 йилда "Аёллар дафтари"га киритилиб, бир марталик 600 минг сум миқдорида моддий ёрдам олган.
B15: 13 | C15: 2000 | D15: 45348 | F15: Барча туман,шаҳарларда ПҚ-306-сонли қарор бўйича жорий йилнинг 15 мартига қадар ҳар бир маҳаллада камида 1 тадан лойиҳаларни Бизнес портал платформасига киритиб Сертификат олиб, кредит ажратилиши белгиланган. Бугунги кунгача 724 та мфйдан 184 тасидан киритилган лойихалар Сертификат олиб банкка юборилган. Қолган 540 та МФЙда киритилган лойихалар Сертификат олмаган. Ушбу ишларни жадаллаштириш учун 3 кун муддатда киритилган лойихаларни қайта кўриб чиқиб, Туман шаҳар ҳокимлари ва уларнинг биринчи ўринбосарлари Сертификат олишни тезлаштирсин. | G15: 45392 | I15: Термиз шаҳар, Ангор, Бандихон, Бойсун, Денов, Жарқўрғон, Қизириқ, Қумқўрғон, Музработ, Олтинсой, Сариосиё, Узун, Термиз туман, Шеробод, Шўрчи туман ҳокимлари, туман хокимларининг биринчи ўринбосарлар, туман ва шаҳарлардаги маҳаллабай марказлари | L15: 25.03.2024 й ҳолатига Жами 156 та мфйда ташкил этилмаган. Термиз шаҳар 7 та, Ангор 4 та, Бандихон 3 та, Бойсун 13 та, Денов 50 та, Жарқўрғон 11 та, Қумқўрғон 3 та, Музработ 8 та, Олтинсой 10 та, Сариосиё 20 та, Термиз туман 3 та, Узун 10 та, Шеробод 10 та, Шўрчи 4 та мфйларда бирорта ҳам лойихалар сертификат олмаган, банкка юборилмаган.
B16: 14 | C16: 2004 | D16: 45352 | F16: Шеробод туманида Автомактабга бориш йулида бордюр ва освещение ўрнатиш. (Ўрнатилгандан сўнг вилоят Автойул бошкармаси М.Алламурадов асфальтлаш ишларини амалга оширсин) | G16: 45390 | I16: Шеробод тумани хокими Алимов | L16: Дастлабки ишлари бошланган.
B17: 15 | C17: 2005 | D17: 45352 | F17: Термиз шахар Исо Ат Термизий кўчасидаги уйларнинг фасад кисмларини созлаш, йўлларини тўгирлаш хамда ободонлаштириш ишларини амалга ошириш | G17: 45384 | I17: Термиз шаҳар ҳокими Ў.Тўраев Халк кабулхонаси А.Эшмуродов
B18: 16 | C18: 2006 | D18: 45352 | F18: Хўжаипок насос станциясини куёш панелига ўтказиш ва дебитор кредитор карздорликларини аниклаш. | G18: 38079 | I18: Курилиш мажмуаси котибият мудири Н.Тўракулов Иктисодиёт ва Молия бош бошкармаси бошлиги Ж.Нормўминов | L18: Ўрганилмоқда
B19: 17 | C19: 2010 | D19: 45352 | F19: Денов туманидаги бозорда ишламай турган дўконларни ишсизлар ҳисобига тўлдириш, иш билан таъминланганлик даражасини ошириш | G19: 45387 | I19: Вилоят Солик бошкармаси (Э.Нарманов) А.Орипов Денов тумани 4та сектор рахбарларига | L19: Denov tumanida joylashgan “Muxammadali” MChJ hududidan 167 nafar tadbirkorlik faoliyati bilan shug`ullanish istagi bor ishsiz yoshlarga do‘konlar ajratilib, tadbirkorlik faoliyatlarini yo‘lga qo‘yishlari uchun kerakli amaliy yordamlar ko‘rsatildi/ (Солиқ бошқармасининг 2024 йил 5 мартдаги 14-15880 сонли хат)
B20: 18 | C20: 2012 | D20: 45352 | F20: Ёшларни ҳарбий сафарбарликка тайёрлаш бўйича дарс синфхоналарини 100 фоиз жиҳозлаш. | G20: 45386 | I20: Иктисодиёт ва Молия бош бошкармаси бошлиги Ж.Нормўминов Вилоят Мактабгача ва мактаб таълими бошкармаси (Ҳ.Мамадиев) | L20: Вилоят ХТБ 05.03.2024 й 01-638 сонли хат билан Мудофаа саноати агентлигига Чакирувга кадар бошлангич тайёргалик фани хонаси учун зарур булган жихозлар нархларини аниклаб беришида амалий ёрдам сураб чиккан.
B21: 19 | C21: 2014 | D21: 45352 | F21: Мактабгача ва мактаб таълими тизимида КПИ тизимини жойига кўйиш | I21: Вилоят Мактабгача ва мактаб таълими бошкармаси (Ҳ.Мамадиев) | L21: Лойиҳа ишлаб чиқилмоқда
B22: 20 | C22: 2015 | D22: 45352 | F22: Барча мактабларда Оталар йиғилиши ўтказиш керак | G22: 45384 | I22: Вилоят Мактабгача ва мактаб таълими бошкармаси (Ҳ.Мамадиев) Миллий гвардия () | L22: Ҳар шанба ўтказиляпти
B23: 21 | C23: 2016 | D23: 45352 | F23: Мактаблардаги давомат, озик-овкат, аутсорсинг хизматлари бўйича чоршанба кунигача ахборот бериш | G23: 45384 | I23: Вилоят Мактабгача ва мактаб таълими бошкармаси (Ҳ.Мамадиев) Миллий гвардия (Ш.Саидов) И.Сапаров | L23: Ҳар чоршанба маьлумот бериб борилади 06.03.2024 йда маълумот берилди
B24: 22 | C24: 2020 | D24: 45352 | F24: Васийлик ва Ҳомийликка муҳтож бўлган, ота онасидан назоратсиз колиб кетган болалар билан ишлаб, уларнинг мауаммоларини ҳал этиш. | G24: 45397 | I24: Вилоят ҳокимининг ўринбосари И.Сапаров Ижтимоий ҳимоя миллий агентлиги М.Тогаев | L24: Инсон ижтимоий хизматлари маркази вилоят бўлими томонидан шахар ва туманларда ота-она қарамоғисиз, қаровсиз ва назоратсиз қолиб кетган 1330 нафар болалар аниқланди. Шундан 301 нафарига васийлик ва ҳомийликни белгилаш юзасидан шаҳар, туман ҳокимларининг қарорлари қабул қилинди. Қолган 1029 нафар болаларга васий, ҳомий тайинлаш борасида хужжат ишлари олиб борилмоқда. 29.03.2024 й. ҳолати.
B25: 23 | C25: 2035 | D25: 45355 | F25: Фуқаро Рамазонова Турсуной (99-552-04-66) (Сариосиё т.Дашнобод МФЙ) спорт анжомларини ҳомийлик ҳисобидан олиб берилиши тўғрисида. | G25: 45387 | I25: Вилоят ҳокимининг ўринбосари И.Сапаров | L25: Фуқаро билан богланилди. Хеч ким учрашмаган. (18.03.2024 ҳолатига)
B26: 24 | C26: 2036 | D26: 45355 | F26: Фуқаро Сатторова Малоҳат (91-585 -56-40) Гдф дан сув тортиб бериш, трансформаторини таъмирлашга амалий ёрдам бериш тўғрисида | G26: 45362 | I26: Термиз тумани ҳокими Ш.Назаров | L26: Ишлар тўлиқ бажарилгач назоратдан ечилади! Фуқаро М.Сатторова тушунтириш хатида трансформаторини таъмирлаб берилганлигини ёзиб ташаккурнома берган. (17.03.2024 й ҳолати)20.03.2024 й. холатига куча бошига битта кран тортиб берилган. Навруз байрамидан кейин ахолига сув тортилади
B27: 25 | C27: 2053 | D27: 45357 | F27: Ҳамма маҳалла еттиликлари ходимларини яхши ва ёмон ишлаган ходимлари бўйича вилоят ҳокимига кунлик ахборот киритиш | G27: 45387 | I27: Вилоят Маҳалла уюшмаси Ш.Бойқулов Солиқ бошқармаси Э.Нарманов
B28: 26 | C28: 2058 | D28: 45357 | F28: Молия ва Халқ таълими бошқармаси шаҳар ва туман ҳокимлари ЧЁТ хоналарига ўқув жихозлари олиб бериш | G28: 45387 | I28: Вилоят ҳокимининг ўринбосари И.Сапаров Халқ таълими бошқармаси, Шаҳар туман ҳокимлари
B29: 27 | C29: 2060 | D29: 45357 | F29: 2 минг нафар касб эгаллаган битирувчиларни Козон шахридаги коллежда ўқитиш ва ишга жойлаштириш бўйича янги тизим яратиш. | G29: 45386 | I29: Вилоят ҳокимининг ўринбосари И.Сапаров Халқ таълими бошқармаси Х.Мамадиев Камбағалликни қисқартириш ва бандлик бошқармасиО.Якубов | L29: Вилоят Мактабгача ва мактаб таълими бошқармаси ходимларидан иборат делегациясининг Татаристон Республикасига ташрифи режалаштирилган.
B30: 28 | C30: 2062 | D30: 45357 | F30: Наврўзгача барча ДХШларни топшириш | G30: 45370 | I30: Вилоят ҳокимининг ўринбосари И.Сапаров Барча туман ва шаҳар ҳокимликларига | L30: Ангор туманида дорилаш ишлари олиб борилмоқда. Узун туманида дорилаш ишлари олиб борилмоқда. Қизириқ туманида ишлар олиб борилмоқда. Термиз туманида ишлар олиб борилмоқда. Термиз шаҳарда дорилаш ишлари олиб борилди
B31: 29 | C31: 2071 | D31: 45369 | F31: Назаров Мансур (91-512-80-32) Маданий меьрос объекти буйича масаласини ҳал этиш | G31: 45376 | I31: Вилоят ҳокимининг ўринбосари Ж.Тўраев
B32: 30 | C32: 2072 | D32: 45369 | F32: Врач Умид ака (99-411-75-67) Рентген имплант аппарати олиши учун кредит олиш масаласида. Ҳамзаев Соҳибжон (99-767-69-67) | G32: 45376 | I32: Марказий банк А.Тўхтаев | L32: Фуқаронинг номидаги 80 млн. сўм кердит қарздорлиги сўндирилгандан кейин ПҚ-306 сон қарор бўйича ажратилади.(Сухбат баёни бор)
B33: 31 | C33: 2074 | D33: 45369 | F33: Сариосиёда Шоҳқишлоқ МФЙ ни 3 км асфальт қилиш ва шу масала буйича 9 та МФЙ бўйича ахборот бериш | G33: 45376 | I33: А.Амиров | J33: Ж.Тўраев | K33: Бажарилмоқда
B34: 32 | C34: 2075 | D34: 45369 | F34: Сариосиё тумани Шарқ юлдузи, Афросиёб МФЙ ларини газ, сув, электр, ободонлаштириш ишларини охирига етказиш | G34: 45376 | I34: Давлат активларини бошқариш С.Худойбердиев
C35: 2077 | D35: 45369 | F35: Мўминов Шоди (93-226-47-53) гаплашиш кк. Уй жойлари Жаркургон Бандихон чегара зонасида жойлашганлиги, уй жойларини кадастр хужжатларини килишда амалий ёрдам бериш тўғрисида. Мусулмон ота кучасини Жаркургон тумани хисобига колдиришни сураган. | G35: 45376 | I35: Кадастр бошқармаси Жарқўрғон тумани ҳокими | J35: А.Орипов | K35: Бажарилмоқда
B36: 33 | C36: 2079 | D36: 45369 | F36: Раҳмонов (91-078-45-88) Масаласини хал қилиш | G36: 45384 | I36: Вилоят Мактабгача ва мактаб таълими бошқармаси Х.Мамадиев
B37: 34 | C37: 2080 | D37: 45369 | F37: Қизириқ туманидаги 2 гектар иссикхона кредит масаласи бўйича туман прокурори жиноят иши қўзғатиши керак | G37: 45376 | I37: Қизириқ туман прокуратураси
B38: 35 | C38: 2082 | D38: 45369 | F38: Расулова Фароғат (97-809-81-24) Тошкентга даволанишига боришида амалий ёрдам бериш | G38: 45392 | I38: Вилоят Соғликни сақлаш бошқармасиК.Абдувоҳидов | J38: И.Сапаров | K38: Бажарилмоқда
B39: 36 | C39: 2090 | D39: 45371 | F39: Қумқурғон туманидаги фуқаро Ўрин Худойбердиевнинг (91-580-06-54) уйига кириладиган йўлни 100 метр жойини бетонлаш | G39: 45378 | I39: А.Нормаматов Қумқўрғон тумани ҳокими
B40: 37 | C40: 2091 | D40: 45371 | F40: Қумқўрғон туманидаги фуқаро Ўрин Худойбердиевнинг (91-580-06-54) қизига электрон кроват обериш. | G40: 45435 | I40: М.Тоғаев Ижтимоий ҳимоя миллий агентлиги вилоят бўлими
B41: 38 | C41: 2094 | D41: 45371 | F41: Қумқўрғон т. Фуқаро Холматов Нурзод (97-179-39-93) снос ва уй-жой масаласини ҳал қилиш | G41: 45390 | I41: Қумқўрғон тумани ҳокими А.Нормаматов
B42: 39 | C42: 2095 | D42: 45371 | F42: Қумқўрғон тумани 12 сонли МТТ га (мудира Сафарова Феруза 93-799-25-05) беседка қилиб бериш | G42: 45387 | I42: Қумқўрғон тумани ҳокими А.Нормаматов
B43: 41 | C43: 2099 | D43: 45371 | F43: Заковатчи қизларга ва уларнинг (24 та мактаб) ўқитувчиларига совға тайёрлаш ва биттадан чет тили хоналарини тўғирлаш | G43: 45381 | I43: Ж.Нормўминов Иқтисодиёт ва Молия бош бошқармаси бошлиғи
B44: 42 | C44: 2100 | D44: 45374 | F44: Термиз шаҳрида яшовчи фуқаро Боботова Улбош (93-791-29-58) қизини уй-жой бериш масаласини ўрганиб чиқиш. | G44: 45386 | I44: Ў.Тўраев Термиз шаҳар ҳокими
B45: 43 | C45: 2101 | D45: 45374 | F45: Қизил тоифадаги маҳаллаларни 1 ой муддатда яшил тоифага ўтказиш | G45: 45402 | I45: Шаҳар, туман ҳокимларининг 1-ўринбосарлари
B46: 44 | C46: 2104 | D46: 45374 | F46: Банкларга бириктирилган биттадан маҳаллаларини тартибга келтириб, биттадан кўчаларни намуна қилиб тайёрлаш | G46: 45385 | I46: Барча тижорат банклари
B47: 45 | C47: 2105 | D47: 45374 | F47: Қумқўрғон тумани Богаро маҳалласига 15 кун муддатда сув чиқариш | G47: 45389 | I47: Қумқўрғон тумани ҳокими А.Нормаматов
B48: 46 | C48: 2106 | D48: 45374 | F48: Жарқўрғон туманидаги кластерларга берилган иссиқхонани ҳамда Янги Ўзбекистон массивидаги қурилиши якунланмаган бинони якунлаш. | G48: 45407 | I48: Э.Авазов Жарқўрғон тумани ҳокими
B49: 47 | C49: 2107 | D49: 45374 | F49: Жарқўрғон туманидаги ёшлар кичик саноат зонасини тайёр ҳолга келтириш | G49: 45407 | I49: А.Орипов Э.Авазов Жарқўрғон тумани ҳокими
B50: 48 | C50: 2108 | D50: 45374 | F50: Жарқўрғон туманидаги 33-мактабнинг битта чет тили хонасини жиҳозлаш | G50: 45385 | I50: Ж.Нормўминов Иқтисодиёт ва Молия бош бошқармаси бошлиғи
... B52: 50 | C52: 2110 | D52: 45374 | F52: Жарқўрғон тумани Қораёғоч маҳалласига 54та симёғоч ва 300 метр асфальт қилиш. (Маҳалла раиси Шамсиддин 90-134-85-18) | G52: 45389 | I52: Автомобил йўллари бош бошкармаси (М.Алламуродов), Ҳудудий электр тармоқлари" АЖ (М.Шамсиддинов)
B53: 51 | C53: 2111 | D53: 23.03.202 | F53: Жарқўрғон тумани Қораёғоч маҳалласида яшовчи фуқаро Қурбонова Маърифатни (94-980-57-45) Мактабгача таълим ташкилотига ишга жойлаштириш | G53: 45389 | I53: Вилоят Мактабгача ва мактаб таълими бошқармаси Х.Мамадиев
B54: 52 | C54: 2112 | D54: 45345 | F54: Жарқўрғон тумани Қораёғоч маҳалласида яшовчи фуқаро Боймирзаев Илҳомга (93-755-81-56) уй-жой қилиб бериш масаласида | G54: 45392 | I54: Жарқўрғон тумани прокурори
B55: 53 | C55: 2113 | D55: 45381 | F55: Вилоятдаги чиқинди полигонлари атрофига дарахт кўчатларини экиш | G55: 45387 | I55: Бойсун Денов Жарқўрғон Қумқўрғон Олтинсой Шеробод Шўрчи Музработ Узун Сариосиё Қизириқ Ангор Термиз туман ҳокимлари, барча туман ҳокимларнинг қурилиш бўйича ўринбосарлари
B56: 54 | C56: 2114 | D56: 45381 | F56: Бойсун тумани Хўжабулғон маҳалласига 10 кун муддатда башнядан сув чиқариш масаласини ҳал этиш | G56: 45390 | I56: А.Амиров А.Арабов Сурхондарё сув таъминоти Б.Шукуров Бойсун тумани ҳокими
B57: 55 | C57: 2115 | D57: 45381 | F57: Бойсун тумани 13-боғчага Яшил макон дастури бўйича дарахт экиш | G57: 45388 | I57: 13-Боғча мудири Х.Мамадиев Вилоят Мактабгача ва мактаб таълими бошқармаси
B58: 56 | C58: 2116 | D58: 45381 | F58: Бойсун Хўжабулғон маҳалласи еттилиги 14 та оилани камбағалликдан чиқариши керак. | G58: 45388 | I58: Б.Шукуров Бойсун тумани ҳокими, туман ҳокимининг биринчи ўринбосари
B59: 57 | C59: 2117 | D59: 45383 | F59: Амударё соҳилидаги зовурларни тозалаш | G59: 45413 | I59: Б.Алимов (Аму Сурхон ИТХБ)

Sheet Каттага бажарилмаган
A1: Вилоят ҳокими У.Қосимов томонидан ҳудудларни ўрганиш давомида аниқланган муаммоларни бартараф этиш бўйича берилаётган тезкор топшириқларнинг ижроси тўғрисида МАЪЛУМОТ (01.04.2024) Бажарилмаган
A3: Т/Р | B3: Банд | C3: Топшириқ берилган сана | D3: Топшириқ берилган жой | E3: Топшириқ мазмуни | F3: Ижро муддати | G3: Назорат ҳолати | H3: Асосий ижрочи маъсуллар | I3: Вилоят ҳокимлиги, шаҳар ва туман ҳокимликлари масъуллар | J3: Ижро ҳолати | K3: Изоҳ
A4: 1 | B4: 1867 | C4: 45271 | E4: Жарқўрғон тумани "А.Навоий" маҳалласидаги ички йўлларни асфалтлаш. (МФЙ раиси Қорақулов Алибой ака 99-753-70-68) | F4: 45361 | H4: Автомобил йўллари бош бошкармаси (М.Алламуродов), Жарқўрғон тумани хокими Э.Авазов | K4: Ички кўчалар асфалтлаш ишлари бошлангани йўқ.
A5: 2 | B5: 1938 | C5: 45336 | E5: Ангор тумани "Новшахар" маҳалласидаги Коллекторларни қазиш. | F5: 45383 | H5: “Аму-Сурхон” ирригация тизимлари хавза бошкармаси бошлиғи Б.Алимов, Ангор тумани хокими Қ.Мардонов. Ангор тумани прокурори | I5: Шаҳар ва туман ҳокимликлари | J5: Бажарилмоқда | K5: Дастур тасдикланди ВМнинг 7.03.2024 йдаги 04-04/1-3362 йиғилиш баёни. (12.03.24й) Коллекторларни қазиш ишлари бажарилмоқда.Ангор тумани Новшахар ва Чинобод махаллалари худудларидаги 25,6 км узунликдаги коллекторларни таъмирлаш-тиклаш ишлари 2024 йил Давлат дастурига киритилган.Шу дастур асосида таъмирлаш-тиклаш ишлари бажарилади. Сурхондарё вилоят хокимининг,кишлок ва сув хужалиги масалалари буйича уринбосари Ф.Исмоилов томонидан 2024 йил 31 январ куни №13-01/98 сонли йигилиш баёни чикарилган.
A6: 3 | B6: 1951 | C6: 45346 | E6: "Ҳудудий электр тармоқлари" АЖ (М.Шамсиддинов) 4 та объектни бир хафта муддатда топшириши керак. | F6: 45383 | H6: Ҳудудий электр тармоқлари" АЖ (М.Шамсиддинов) | K6: Опен бюджетдаги 3 та объект (Олтинсой т, Қизилтепа МФЙ раиси бн богланилди, ишлар давом этмоқда. Сариосиё тумани Бойсунобод МФЙ раиси бн богланилди ишлар давом этмоқда, Турмушобод маҳалласи раиси бн богланилди ишлар давом этмоқда) Колган 1та (Денов Тасмасой маҳалласи) обьектни амалга ошириш учун 1 хафта муддат сурамокда. 02.03.2024 й холатига
A7: 4 | B7: 1961 | C7: 45346 | D7: Шўрчи тумани | E7: "Минтақавий йўлларга буюртмачи ҳизмати" ДУК (А.Боқиев) Шўрчи тумани "Жойилма" мфйдаги 1,5 км ва Қумқўрғон тумани "Сурхон сохили" мфйдаги 2,5 км ички йўлларни асфалтлаш бўйича берилган топшириқни шанба кунига қадар йўлни тугатиши керак. | F7: 45383 | H7: Кумкургон ТЕФУК Нормуминов "Минтақавий йўлларга буюртмачи ҳизмати" ДУК | I7: А.Орипов | J7: Бажарилмоқда | K7: Материаллар захираси яратилган.
A8: 5 | B8: 1987 | C8: 45349 | E8: Музработ ва Термиз туманидаги парранда комплексларини кейинги сешанба кунига қадар ишга тушириш керак. | F8: 45356 | H8: Вилоят хокимининг ўринбосари Ф.Исмоилов, Вилоят Агробанк Ш.Ражабов. | K8: Музробот туманидаги “Мовароуннахр” паррандачиликка ихтисослашган фермер хўжалигида бугунги кунда жами 80 минг бош паррандалар парваришланмоқда. Шундан 40 минг бош она товукларни ташкил қилади, корхона томонидан кунига 35 минг дона тухум ишлаб чиқарилмоқда. Фермер хўжалигига 5 гектар сувли ер майдон ажратилган бўлиб, хозирги кунда 15 нафар ишчи доимий ишлаб қелмоқда. Бугунги кунда хўжалик фаолиятини кенгайтириш мақсадида 3 млрд сўм банк кредити сўраб мурожаат қилган. Бироқ хозирда хўжалигнинг Ўзсаноатқурилиш банкдан 380 минг АҚШ доллари миқдорида кредит қарздорлиги бўлганлиги сабабли кредит ажратилмаган. Ўзсаноатқурилиш банк томонидан мавжуд кредит қарздорлик муддатини узайтириш бўйича ишлар олиб борилмоқда. Рахбари: Курбон 99-675-10-78 Термиз туманидаги “Турсунтош парранда” масъулияти чекланган жамияти томонидан 2023 йил дастурга киритилган. Бугунги кунда жамият томонидан 300 минг бошга мўлжалланган паррандачилик комплекси қуриб битказилган бўлиб хозирда 70 минг бошга мўлажалланган асбоб ускуналар тўлиқ ўрнатилган. Корхонага парранда олиб келиш учун Агробанкдан имтиёзли кредит сўраб мурожаат қилган. Агробанкда паррандачилик учун имтиёзли кредит йўқлиги сабабли тижорат кредити 25 фоиздан таклиф қилинмоқда. Хозирги кунда корхона томонидан хисоб рақамини Микрокредит банкка ўтказиш ишлари олиб борилмоқда. Рахбари: Аброр 99-712-02-08
A9: 6 | B9: 2024 | C9: 45352 | E9: Сариосиё тумани Дустлик МФЙ, Шабнам МФЙ раисларининг ойлигидан 30% жарима,Тортули солик инспектори ва Тортули МФЙ ҳоким ёрдамчиси Ш.Бекмуродовни ойлигидан 30% жарима, Тортули МФЙ Хотин кизлар фаолини ойлигидан 30% жарима | F9: 45357 | H9: Сариосиё тумани ҳокими | K9: Вилоят Солиқ бошқармасининг 2024 йил 7 мартдаги 29-16240 сонли хати. Солиқ бошқармасининг 06.03.2024 й.даги 00082-сонли буйруғи билан Сариосиё тумани Тортули маҳалласига бириктирилган солиқ инспекторига нисбатан 30% миқдорда жарима жазоси тайинланди.
A10: 7 | B10: 2025 | C10: 45352 | E10: Узун тумани Иттифоқ, Гулистон, Янги рўзғор, Қарашиқ, Наврўз, Дехқон МФЙ раислари ойлигидан 30% жарима, Қарашиқ, Хурсанд, Янгиобод, Дуғоб ва Нурли келажак МФЙ ҳоким ёрдамчиларининг ойлигидан 30% жарима, Нурафшон маҳалласининг ҳоким ёрдамчиси И.Рўзиевни лавозимидан озод этиш. | F10: 45357 | H10: Узун тумани ҳокими | K10: Узун тумани Иттифоқ, Гулистон, Янги рўзғор, Қарашиқ, Наврўз, МФЙ раислари ойлигидан 30% жарима, Қарашиқ, Хурсанд, Янгиобод, Дуғоб ва Нурли келажак МФЙ ҳоким ёрдамчиларининг ойлигидан 30% жарима, Нурафшон маҳалласининг ҳоким ёрдамчиси И.Рўзиега "хайфсан" интизомий жазоси берилган. Ушбу кўрсатилган барча ходимлардан тушинтириш хати олинди
A11: 8 | B11: 2030 | C11: 45355 | E11: Термиз туманида иккита иссиқхона фаолиятини йўлга қўйиш бўйича | F11: 45362 | H11: Вилоят Асака банк бошлиги Б.Тўраев Термиз тумани ҳокими | K11: Иссикхона қурилган ер майдони бошка ташкилотга тегишли бўлганлиги сабабли, янги салоҳиятли ташаббускор номига расмийлаштириш имконияти бўлмай турганлиги, Таклиф: Қурилган иссикхонани ер майдонини дастлабки эгасининг номидан қарздор корхона номига расмийлаштиришда амалий ёрдам зарурлиги, шундан сунг карздор корхонанинг номидан янги ташаббускорга расмийлаштириш имконияти мавжуд булади. Асака банк вилоят филиалининг 26.03.2024 йдаги 1912-14/680 сонли хати
A12: 9 | B12: 2033 | C12: 45355 | E12: Фуқаро Қурбоналиева Жамилани (93-761-11-17) ишга жойлаштиришга амалий ёрдам бериш | F12: 45357 | H12: Вилоят ҳокимининг биринчи ўринбосари А.Орипов Марказий банк вилоят бош бошқармаси А.Тўхтаев | K12: Ж.Қурбановага иш таклиф қилинган, асосий штатдан иш қилиб беришни сўряпти.Бугунги кунда штат очилиш ишлар бажрилмоқда.
A13: 10 | B13: 2037 | C13: 45357 | E13: Барча мактабгача таълим муассасаларида гимнастика хонаси ташкил этиш бўйича | F13: 45377 | H13: Вилоят ҳокимининг ўринбосари И.Сапаров Мактабгача ва мактаб таълими бошқармаси Х.Мамадиев Вилоят Спорт бошқармаси Б.Тўрабоев | K13: Барча МТМларда Гимнастика хонаси ташкил этиш бўйича берилган топшириққа асосан ишлар давом этмоқда.
A14: 11 | B14: 2069 | C14: 45369 | E14: Мурдов Фахриддин (88-844-33-34) Маблаг масаласини хал килиш | F14: 45376 | H14: Ягона буюртмачи хизмати А.Сувонқулов Иктисодиёт ва Молия бошқармаси Ж.Нормуминов | I14: И.Сапаров | K14: Вилоят ХТБ 05.03.2024 й 01-638 сонли хат билан Мудофаа саноати агентлигига Чакирувга кадар бошлангич тайёргалик фани хонаси учун зарур булган жихозлар нархларини аниклаб беришида амалий ёрдам сураб чиккан.
A15: 12 | B15: 2070 | C15: 45369 | E15: Султонов Сафарали (91-517-27-77) Маблағ масаласини ҳал этиш | F15: 45376 | H15: Ягона буюртмачи хизмати А.Сувонқулов Иктисодиёт ва Молия бошқармаси Ж.Нормуминов | K15: Вилоят Мактабгача ва мактаб таълими бошқармасининг 25.03.2024 й.даги 01-550 сонли хати. Ишлар давом этмоқда
A16: 13 | B16: 2086 | C16: 45369 | E16: Файзиддин асаларичига 99-445-85-41 субсидия бериш масаласида. | F16: 45371 | H16: Камбағалликни қисқартириш ва бандлик бошқармаси О.Якубов Бойсун тумани ҳокими Б.Шукуров
A17: 14 | B17: 2087 | C17: 45369 | E17: Бойсун туманидаги тадбиркорга Халк банки кредит чиқариши керак | F17: 45376 | H17: Вилоят Халқ банки А.Юлдашев
A18: 15 | B18: 2096 | C18: 45371 | E18: Қумқўрғон тумани Янгиер маҳалласида Лойиҳаларни ишлаб чиқиш | F18: 45378 | H18: Ю.Менглиев Вилоят Ичимлик сув ва оқова сув қурилиши бўйича инжинеринг компанияси вилоят бўлими Ж.Рўзиев Вилоят Тог кон Геология ва саноат хавфсизлигини назорат қилиш инспекцияси
A19: 16 | B19: 2098 | C19: 45371 | E19: Қумқўрғон т. фуқаро Жасурбек Хуррамов (99-666-25-65, 93-991-07-20) башня масаласини ҳал қилиш | F19: 45378 | H19: Ю.Менглиев Вилоят Ичимлик сув ва оқова сув қурилиши бўйича инжинеринг компанияси вилоят бўлими
A20: 17 | B20: 2102 | C20: 45374 | E20: Душанба куни бўш турган биноларни жадвал кўринишида ҳисоботини бериш | F20: 45383 | H20: А.Орипов
A21: 18 | B21: 2103 | C21: 45374 | E21: Қумқўрғон туманида битмай қолган КВПни битқазиш чораларини кўриш ва сабабларини ўрганиб чиқиш | F21: 45383 | H21: И.Сапаров К.Абдивоҳидов Вилоят Соғликни сақлаш бошқармаси

Sheet Юлдузча
A1: Вилоят ҳокими У.Қосимов томонидан ҳудудларни ўрганиш давомида аниқланган муаммоларни бартараф этиш бўйича берилаётган тезкор топшириқларнинг ижроси тўғрисида МАЪЛУМОТ (04.05.2023)*
A3: Т/Р | B3: Банд | C3: Топшириқ берилган сана | D3: Топшириқ берилган жой | E3: Топшириқ мазмуни | F3: Ижро муддати | H3: Асосий ижрочи маъсуллар | I3: Вилоят ҳокимлиги, шаҳар ва туман ҳокимликлари масъуллар | J3: Ижро ҳолати | K3: Изох
A4: 1 | B4: 251 | C4: 09.01.2023 | D4: Ангор тумани | E4: Ангор тумани "Гиламбоб" МФЙдаги “Ангор пахта тозалаш” АЖга қарашли Таллимарон пахта қабул қилиш маскани биносидан самарали фойдаланиш мақсадида хизмат кўрсатиш нуқталари ва маҳалла гузари ташкил этиш. | F4: 45045 | G4: Билдирги | H4: Вилоят МИБ Ўздаверлойиҳа институти вилоят бўлинмаси (Э.Ражабов), Марказий банк бошқармаси (А.Тўхтаев), Ангор тумани ҳокимлиги | I4: А.Орипов | J4: Бажарилмаган | K4: Аукционга қўйилган. Тадбиркор ютиб олиши керак.
A5: 2 | B5: 348 | C5: 05.01.2023 | D5: Тақдимотда | E5: "Мамик Коппер" МЧЖни мис ишлаб чиқаришни ташкил этиш лойиҳасини амалга ошириш чора-тадбирларини белгилаш мақсадида ташаббускор билан учрашув ташкил этиш. | F5: 45047 | G5: Билдирги | H5: Узун тумани ҳокими Б.Турсунов | I5: С.Ўралов | J5: Бажарилмаган | K5: Тадбиркор Туркияда июл ёки август ойида келаман деган. Тадбиркорни мис ишлаб чиқариш учун 2026 йилгача литцензияси бор
A6: 3 | B6: 829 | C6: 44950 | D6: Штаб йиғилиши | E6: Қизириқ, Қумқўрғон, Термиз ҳамда Шеробод туманлари бугунги кунгача ишга тушмасдан қолган 7 та лойиҳаларни 1 ҳафта муддатда ишга туширилишини таъминласин натижаси бўйича ҳисобот берсин. | F6: 45051 | G6: Билдирги | H6: Термиз туман ҳокимлиги | I6: С.Ўралов | J6: Бажарилмоқда | K6: 7 та лойихадан 1 та "Shohruh" MCHJ қолган. 01.05.2023 й Хукумат комиссиясини протоколига асосан муддати 28.12.2023 йилга қадар узайтирилган.
A7: 4 | B7: 856 | C7: 28.01.2023 | D7: Бойсун тумани Сайроб МФЙ | E7: Бойсун туманидаги "Бойсун Қурилиш Сантехника" МЧЖга ҚОП ва мактаб биносини қуриш ишлари учун буюртмачи томонидан маблағлар тўлаб берилишини таъминлаш. | F7: 45031 | H7: Молия бош бошқармаси (Ж.Нормўминов), «Ягона буюртмачи хизмати» ИК (А.Арамов). | I7: А.Хидиров | J7: Бажарилмаган | K7: Жами 483 млн сўм маблағлар молиялаштирилган. 1-чорак якунлари билан қўшимча маблағлар ажратилиши режалаштирилган. Бироқ ҳозирда маблағлар ажратилмаган. Қурилишларни тамомлаш учун яна 1 млрд 934 млн сўм маблағлар талаб этилмоқда.
A8: 5 | B8: 989 | C8: 03.02.2023 | D8: Сурхон Арена спорт мажмуаси | E8: Сурхондарё вилояти полвонлари учун Кураш марказини ташкил қилиш тизимини ишлаб чиқиб вилоят ҳокимига кириш. | F8: 45056 | H8: Спортни ривожлантириш бошқармаси (А.Арабов) | I8: И.Сапаров | J8: Бажарилмоқда | K8: ЛХС ишлаб чиқилган. Қурилиш ишлари "Проф Гроуп" МЧЖ томонидан бошланган
A9: 6 | B9: 991 | C9: 03.02.2023 | D9: Сурхон Арена спорт мажмуаси | E9: Ал-Ҳаким ат-Термизий хотирасига бағишланган Кураш бўйича Жахон чемпионатини юқори даражада ташкил қилиш мақсадида чора-тадбирлар дастурини ишлаб чиқиб, тасдиқга киритиш. | F9: 45056 | H9: Спортни ривожлантириш бошқармаси (А.Арабов) | I9: И.Сапаров | J9: Бажарилмоқда | K9: Мусобақа октябр ойига қолдирилган бўлиши мумкин. Мазкур чора-тадбирлар лойихаси вилоят хокимлиги девонхонасига 31.03.2023 йил 01-26/572-тартиб ракам билан кирим килинган
A10: 7 | B10: 1059 | C10: 09.02.2023 | D10: Термиз шаҳри | E10: Термиз шаҳридаги Шарқ меҳмонхонаси ёнида қурилган бинога рухсат бериш ҳужжатларини қайта ўрганиб, ахборот бериш. | F10: 45056 | G10: Билдирги | H10: Термиз шаҳар ҳокими Ў.Тўраев, Қурилиш бош бошқармаси (К.Эшматов) | I10: А.Хидиров | J10: Бажарилмоқда | K10: Термиз шаҳар судга даъво ариза киритиши керак эди. Термиз шаҳар даво аризасини киритган.
A11: 8 | B11: 1073 | C11: 10.02.2023 | D11: Алпомиш арена | E11: Алпомиш аренада ўтказилиши белгиланган кураш мусобақасига тайёргарлик ишларига курашчилар учун яктаклар тикувчи ва кураш татами, гиламларини ўрнатувчиларни тайёргарлик ишларига жалб қилиш. | F11: 45056 | H11: Вилоят ҳокимининг ўринбосарлари И.Сапаров ва Ж.Тўраев, Спортни ривожлантириш бош бошқармаси (А.Арабов). | I11: И.Сапаров | J11: Бажарилмоқда | K11: Мусобақа октябр ойига қолдирилган бўлиши мумкин.
A12: 9 | B12: 1077 | C12: 10.02.2023 | D12: Алпомиш арена | E12: Алпомиш аренадаги мавдуж эски жихозларни (мебел, офис) тегишли тартибда туманларга бериш ва арена жихозларини янгилаш. | F12: 45051 | H12: Вилоят хокимлиги «Ягона буюртмачи хизмати» ИК (А.Арамов), Спортни ривожлантириш бош бошқармаси (А.Арабов). | I12: И.Сапаров | J12: Бажарилмоқда | K12: Молиялаштириш манбаси аниқ эмас. 1 млрд 663 млн сўм маблағлар талаб этилмоқда
A13: 10 | B13: 1338 | C13: 45016 | D13: Бандихон тумани | E13: Бандихон тумани "Хўжаипок" маҳалласи ҳудудида 37 гектар адирликда сув чиқариб ерларни ўзлаштирган Тожимурод бобони ёнидан қўшимча ер майдонларини аниқлаб савдога чиқариш. | F13: 45036 | H13: Кадастр палатаси (С.Шоймардонов), Кадастр агентлиги (М.Абдурахмонов), Бандихон туман хокимлиги | I13: Бандихон тумани | J13: Бажарилмаган | K13: 78,2 гектар ер майдонлари аниқланиб, туман Халқ депутатлари кенгашидан ўтказилган. Аукционга чиқариш чоралари кўрилмоқда.
A14: 11 | B14: 1341 | C14: 45016 | D14: Ипподромда | E14: Бойсун туманида уй олмоқчи бўлган 220 нафар фуқароларни рўйхатини шакллантириш, уйларни тегишли тартибда расмийлаштириш бўйича ишларини якунлаш. | F14: 45066 | H14: Бойсун туман хокими ва сектор рахбарлари Марказий банк бош бошқармаси (А.Тўхтаев), Қишлоққурилишбанк (Ж.Қодирқулов) | I14: Бойсун тумани | J14: Бажарилмоқда | K14: 151 та мижоз билан шартномалар қилинган. Қолган уйларни қурилиш ишлари йил якунига қадар чўзилиши мумкин.
A15: 12 | B15: 1369 | C15: 45019 | D15: Зоом йиғилиш | E15: Денов тумани Фермер, деҳқон хўжаликлари ва томорқа ер эгалари кенгаши раисига хайфсан бериш. | F15: 45051 | H15: Денов тумани хокими И.Аброров | I15: Ф.Менглиев | J15: Бажарилмоқда | K15: "Ўзбекистон" қахрамони унвони сохиби экан.
A16: 13 | B16: 1446 | C16: 45038 | D16: Термиз шаҳар | E16: Термиз шаҳар "Тупроққўрғон" маҳалласидаги кўп қаватли уйга ёпиштириб қурган икки қаватли дўкон биносини қурилишини қонуний ёки ноқонунийлигини ўрганиш ҳамда тегишли чора-тадбирларни белгилаш керак. | F16: 45051 | H16: Қурилиш бош бошқармаси (К.Эшматов), Давлат Кадастрлар палатаси вилоят бошқармаси (С.Шаймарданов), Термиз шаҳар хокими Ў.Тўраев ва сектор рахбарлари | I16: Термиз шаҳар | J16: Бажарилмоқда | K16: Қурилиш бошқармаси ноқонуний қурилишни бартараф этиш бўйича огохлантириш хати берган. Бинони АПЗси йўқ (Архитектура режалаштириш топшириғи йўқ)
A17: 14 | B17: 1467 | C17: 45042 | D17: Ангор туманида | E17: Тижорат банклари автобуслар харид қилиш бўйича лойиҳа ташаббускорлари рўйхатини олиб кириш | F17: 45048 | H17: Марказий банк (А.Тўхтаев), барча тижорат банк раҳбарлари | I17: А.Орипов | J17: Бажарилмаган | K17: Раҳбариятдан сўраш керак
A18: 15 | B18: 1470 | C18: 45042 | D18: Ангор туманида | E18: Бандихон ва Олтинсой туманларида Автовокзал қуриш бўйича ташаббускорларни чақиртириш. | F18: 45044 | H18: Вилоят хокимининг ўринбосари А.Хидиров, Бандихон ва Олтинсой туман хокимликлари | I18: А.Хидиров | J18: Бажарилмаган | K18: Раҳбариятдан сўраш керак
A19: 16 | B19: 1471 | C19: 45042 | D19: Ангор туманида | E19: Қизириқ автошоҳбекатини фойдаланишга қабул қилиб, ахборот бериш | F19: 45044 | H19: Қизириқ туман ҳокими | I19: А.Хидиров | J19: Бажарилмаган | K19: ШНК талабларига мос келмаётганлиги учун Гасн хулоса бермаяпти. Автошохбекат атрофида ноқонуний қурилишлар бор
A20: 17 | B20: 1504 | C20: 45001 | D20: Қизириқ тумани | E20: Қизириқ туманидаги Гулабод маҳалласида қурилаётган савдо комплекси мажмуаси учун ажратилган кредит маблағини қайтариш чораларини кўриш | F20: 45026 | H20: Қизириқ туман ҳокими ҳамда Марказий банк А.Тўхтаев | I20: Қизириқ тумани | J20: Бажарилмаган | K20: Раҳбариятдан сўраш керак
